[
  {"name":"MG_002_MONOMER","imports":["MG_002_MONOMER", "MG_007_MONOMER", "MG_022_MONOMER", "MG_024_MONOMER", "MG_027_MONOMER", "MG_028_MONOMER", "MG_043_MONOMER", "MG_044_MONOMER", "MG_050_MONOMER", "MG_054_MONOMER", "MG_055_MONOMER", "MG_056_MONOMER", "MG_069_MONOMER", "MG_070_MONOMER", "MG_088_MONOMER", "MG_094_MONOMER", "MG_097_MONOMER", "MG_125_MONOMER", "MG_128_MONOMER", "MG_147_MONOMER", "MG_148_MONOMER", "MG_153_MONOMER", "MG_183_MONOMER", "MG_239_MONOMER", "MG_242_MONOMER", "MG_244_MONOMER", "MG_281_MONOMER", "MG_282_MONOMER", "MG_291_MONOMER", "MG_292_MONOMER", "MG_335_MONOMER", "MG_336_MONOMER", "MG_337_MONOMER", "MG_338_MONOMER", "MG_363_MONOMER", "MG_372_MONOMER", "MG_381_MONOMER", "MG_391_MONOMER", "MG_402_MONOMER", "MG_424_MONOMER", "MG_425_MONOMER", "MG_427_MONOMER", "MG_438_MONOMER", "MG_439_MONOMER", "MG_446_MONOMER", "MG_473_MONOMER"]},
  {"name":"MG_007_MONOMER","imports":["MG_002_MONOMER", "MG_007_MONOMER", "MG_009_MONOMER", "MG_024_MONOMER", "MG_026_MONOMER", "MG_027_MONOMER", "MG_028_MONOMER", "MG_043_MONOMER", "MG_044_MONOMER", "MG_050_MONOMER", "MG_054_MONOMER", "MG_055_MONOMER", "MG_056_MONOMER", "MG_069_MONOMER", "MG_070_MONOMER", "MG_088_MONOMER", "MG_094_MONOMER", "MG_097_MONOMER", "MG_105_MONOMER", "MG_113_MONOMER", "MG_125_MONOMER", "MG_128_MONOMER", "MG_147_MONOMER", "MG_148_MONOMER", "MG_169_MONOMER", "MG_180_MONOMER", "MG_183_MONOMER", "MG_205_MONOMER", "MG_239_MONOMER", "MG_242_MONOMER", "MG_244_MONOMER", "MG_281_MONOMER", "MG_282_MONOMER", "MG_291_MONOMER", "MG_292_MONOMER", "MG_306_MONOMER", "MG_317_MONOMER", "MG_335_MONOMER", "MG_336_MONOMER", "MG_337_MONOMER", "MG_344_MONOMER", "MG_363_MONOMER", "MG_372_MONOMER", "MG_381_MONOMER", "MG_402_MONOMER", "MG_424_MONOMER", "MG_425_MONOMER", "MG_427_MONOMER", "MG_428_MONOMER", "MG_438_MONOMER", "MG_439_MONOMER", "MG_446_MONOMER", "MG_458_MONOMER", "MG_469_MONOMER", "MG_473_MONOMER", "MG_498_MONOMER"]},
  {"name":"MG_009_MONOMER","imports":["MG_007_MONOMER", "MG_009_MONOMER", "MG_026_MONOMER", "MG_027_MONOMER", "MG_028_MONOMER", "MG_069_MONOMER", "MG_094_MONOMER", "MG_097_MONOMER", "MG_125_MONOMER", "MG_147_MONOMER", "MG_148_MONOMER", "MG_239_MONOMER", "MG_281_MONOMER", "MG_282_MONOMER", "MG_336_MONOMER", "MG_337_MONOMER", "MG_344_MONOMER", "MG_363_MONOMER", "MG_411_MONOMER", "MG_418_MONOMER", "MG_438_MONOMER", "MG_439_MONOMER", "MG_458_MONOMER"]},
  {"name":"MG_011_MONOMER","imports":["MG_011_MONOMER", "MG_024_MONOMER", "MG_027_MONOMER", "MG_028_MONOMER", "MG_055_MONOMER", "MG_056_MONOMER", "MG_069_MONOMER", "MG_070_MONOMER", "MG_088_MONOMER", "MG_094_MONOMER", "MG_097_MONOMER", "MG_125_MONOMER", "MG_147_MONOMER", "MG_148_MONOMER", "MG_180_MONOMER", "MG_239_MONOMER", "MG_244_MONOMER", "MG_268_MONOMER", "MG_281_MONOMER", "MG_282_MONOMER", "MG_336_MONOMER", "MG_337_MONOMER", "MG_344_MONOMER", "MG_363_MONOMER", "MG_398_MONOMER", "MG_402_MONOMER", "MG_425_MONOMER", "MG_427_MONOMER", "MG_439_MONOMER", "MG_469_MONOMER"]},
  {"name":"MG_022_MONOMER","imports":["MG_002_MONOMER", "MG_022_MONOMER", "MG_024_MONOMER", "MG_026_MONOMER", "MG_027_MONOMER", "MG_028_MONOMER", "MG_043_MONOMER", "MG_044_MONOMER", "MG_055_MONOMER", "MG_056_MONOMER", "MG_069_MONOMER", "MG_070_MONOMER", "MG_088_MONOMER", "MG_097_MONOMER", "MG_125_MONOMER", "MG_141_MONOMER", "MG_153_MONOMER", "MG_182_MONOMER", "MG_183_MONOMER", "MG_239_MONOMER", "MG_242_MONOMER", "MG_244_MONOMER", "MG_275_MONOMER", "MG_281_MONOMER", "MG_282_MONOMER", "MG_293_MONOMER", "MG_336_MONOMER", "MG_337_MONOMER", "MG_360_MONOMER", "MG_402_MONOMER", "MG_428_MONOMER", "MG_439_MONOMER"]},
  {"name":"MG_024_MONOMER","imports":["MG_002_MONOMER", "MG_007_MONOMER", "MG_011_MONOMER", "MG_022_MONOMER", "MG_024_MONOMER", "MG_026_MONOMER", "MG_027_MONOMER", "MG_028_MONOMER", "MG_043_MONOMER", "MG_044_MONOMER", "MG_050_MONOMER", "MG_054_MONOMER", "MG_055_MONOMER", "MG_056_MONOMER", "MG_069_MONOMER", "MG_070_MONOMER", "MG_084_MONOMER", "MG_088_MONOMER", "MG_094_MONOMER", "MG_095_MONOMER", "MG_097_MONOMER", "MG_105_MONOMER", "MG_113_MONOMER", "MG_125_MONOMER", "MG_128_MONOMER", "MG_141_MONOMER", "MG_147_MONOMER", "MG_148_MONOMER", "MG_153_MONOMER", "MG_180_MONOMER", "MG_182_MONOMER", "MG_183_MONOMER", "MG_239_MONOMER", "MG_241_MONOMER", "MG_242_MONOMER", "MG_244_MONOMER", "MG_275_MONOMER", "MG_281_MONOMER", "MG_282_MONOMER", "MG_291_MONOMER", "MG_292_MONOMER", "MG_306_MONOMER", "MG_317_MONOMER", "MG_335_MONOMER", "MG_336_MONOMER", "MG_337_MONOMER", "MG_338_MONOMER", "MG_344_MONOMER", "MG_360_MONOMER", "MG_363_MONOMER", "MG_372_MONOMER", "MG_380_MONOMER", "MG_381_MONOMER", "MG_391_MONOMER", "MG_398_MONOMER", "MG_402_MONOMER", "MG_424_MONOMER", "MG_425_MONOMER", "MG_427_MONOMER", "MG_428_MONOMER", "MG_438_MONOMER", "MG_439_MONOMER", "MG_446_MONOMER", "MG_469_MONOMER", "MG_473_MONOMER", "MG_498_MONOMER"]},
  {"name":"MG_026_MONOMER","imports":["MG_007_MONOMER", "MG_009_MONOMER", "MG_022_MONOMER", "MG_024_MONOMER", "MG_026_MONOMER", "MG_027_MONOMER", "MG_028_MONOMER", "MG_043_MONOMER", "MG_044_MONOMER", "MG_050_MONOMER", "MG_054_MONOMER", "MG_055_MONOMER", "MG_056_MONOMER", "MG_069_MONOMER", "MG_070_MONOMER", "MG_088_MONOMER", "MG_094_MONOMER", "MG_097_MONOMER", "MG_105_MONOMER", "MG_125_MONOMER", "MG_128_MONOMER", "MG_141_MONOMER", "MG_147_MONOMER", "MG_148_MONOMER", "MG_169_MONOMER", "MG_180_MONOMER", "MG_239_MONOMER", "MG_242_MONOMER", "MG_244_MONOMER", "MG_275_MONOMER", "MG_281_MONOMER", "MG_282_MONOMER", "MG_306_MONOMER", "MG_317_MONOMER", "MG_336_MONOMER", "MG_337_MONOMER", "MG_343_MONOMER", "MG_344_MONOMER", "MG_360_MONOMER", "MG_363_MONOMER", "MG_372_MONOMER", "MG_381_MONOMER", "MG_402_MONOMER", "MG_411_MONOMER", "MG_424_MONOMER", "MG_425_MONOMER", "MG_427_MONOMER", "MG_428_MONOMER", "MG_438_MONOMER", "MG_439_MONOMER", "MG_446_MONOMER", "MG_458_MONOMER", "MG_469_MONOMER", "MG_473_MONOMER"]},
  {"name":"MG_027_MONOMER","imports":["MG_002_MONOMER", "MG_007_MONOMER", "MG_009_MONOMER", "MG_011_MONOMER", "MG_022_MONOMER", "MG_024_MONOMER", "MG_026_MONOMER", "MG_027_MONOMER", "MG_028_MONOMER", "MG_043_MONOMER", "MG_044_MONOMER", "MG_050_MONOMER", "MG_054_MONOMER", "MG_055_MONOMER", "MG_056_MONOMER", "MG_069_MONOMER", "MG_070_MONOMER", "MG_084_MONOMER", "MG_088_MONOMER", "MG_094_MONOMER", "MG_097_MONOMER", "MG_105_MONOMER", "MG_113_MONOMER", "MG_125_MONOMER", "MG_128_MONOMER", "MG_141_MONOMER", "MG_147_MONOMER", "MG_148_MONOMER", "MG_153_MONOMER", "MG_169_MONOMER", "MG_180_MONOMER", "MG_183_MONOMER", "MG_205_MONOMER", "MG_239_MONOMER", "MG_241_MONOMER", "MG_242_MONOMER", "MG_244_MONOMER", "MG_275_MONOMER", "MG_281_MONOMER", "MG_282_MONOMER", "MG_291_MONOMER", "MG_292_MONOMER", "MG_306_MONOMER", "MG_317_MONOMER", "MG_335_MONOMER", "MG_336_MONOMER", "MG_337_MONOMER", "MG_343_MONOMER", "MG_344_MONOMER", "MG_360_MONOMER", "MG_363_MONOMER", "MG_372_MONOMER", "MG_380_MONOMER", "MG_381_MONOMER", "MG_391_MONOMER", "MG_398_MONOMER", "MG_402_MONOMER", "MG_411_MONOMER", "MG_418_MONOMER", "MG_424_MONOMER", "MG_425_MONOMER", "MG_427_MONOMER", "MG_428_MONOMER", "MG_438_MONOMER", "MG_439_MONOMER", "MG_446_MONOMER", "MG_458_MONOMER", "MG_469_MONOMER", "MG_473_MONOMER", "MG_498_MONOMER"]},
  {"name":"MG_028_MONOMER","imports":["MG_002_MONOMER", "MG_007_MONOMER", "MG_009_MONOMER", "MG_011_MONOMER", "MG_022_MONOMER", "MG_024_MONOMER", "MG_026_MONOMER", "MG_027_MONOMER", "MG_028_MONOMER", "MG_043_MONOMER", "MG_044_MONOMER", "MG_050_MONOMER", "MG_054_MONOMER", "MG_055_MONOMER", "MG_056_MONOMER", "MG_069_MONOMER", "MG_070_MONOMER", "MG_084_MONOMER", "MG_088_MONOMER", "MG_094_MONOMER", "MG_097_MONOMER", "MG_105_MONOMER", "MG_113_MONOMER", "MG_125_MONOMER", "MG_128_MONOMER", "MG_141_MONOMER", "MG_147_MONOMER", "MG_148_MONOMER", "MG_153_MONOMER", "MG_169_MONOMER", "MG_180_MONOMER", "MG_183_MONOMER", "MG_205_MONOMER", "MG_239_MONOMER", "MG_241_MONOMER", "MG_242_MONOMER", "MG_244_MONOMER", "MG_275_MONOMER", "MG_281_MONOMER", "MG_282_MONOMER", "MG_291_MONOMER", "MG_292_MONOMER", "MG_306_MONOMER", "MG_317_MONOMER", "MG_335_MONOMER", "MG_336_MONOMER", "MG_337_MONOMER", "MG_338_MONOMER", "MG_343_MONOMER", "MG_344_MONOMER", "MG_359_MONOMER", "MG_360_MONOMER", "MG_363_MONOMER", "MG_372_MONOMER", "MG_380_MONOMER", "MG_381_MONOMER", "MG_391_MONOMER", "MG_398_MONOMER", "MG_402_MONOMER", "MG_418_MONOMER", "MG_424_MONOMER", "MG_425_MONOMER", "MG_427_MONOMER", "MG_428_MONOMER", "MG_438_MONOMER", "MG_439_MONOMER", "MG_446_MONOMER", "MG_458_MONOMER", "MG_469_MONOMER", "MG_473_MONOMER", "MG_498_MONOMER"]},
  {"name":"MG_041_MONOMER","imports":["MG_041_MONOMER", "MG_498_MONOMER"]},
  {"name":"MG_043_MONOMER","imports":["MG_002_MONOMER", "MG_007_MONOMER", "MG_022_MONOMER", "MG_024_MONOMER", "MG_026_MONOMER", "MG_027_MONOMER", "MG_028_MONOMER", "MG_043_MONOMER", "MG_044_MONOMER", "MG_050_MONOMER", "MG_054_MONOMER", "MG_055_MONOMER", "MG_056_MONOMER", "MG_069_MONOMER", "MG_070_MONOMER", "MG_088_MONOMER", "MG_094_MONOMER", "MG_097_MONOMER", "MG_105_MONOMER", "MG_125_MONOMER", "MG_141_MONOMER", "MG_147_MONOMER", "MG_148_MONOMER", "MG_153_MONOMER", "MG_169_MONOMER", "MG_180_MONOMER", "MG_183_MONOMER", "MG_239_MONOMER", "MG_241_MONOMER", "MG_242_MONOMER", "MG_244_MONOMER", "MG_275_MONOMER", "MG_281_MONOMER", "MG_282_MONOMER", "MG_293_MONOMER", "MG_317_MONOMER", "MG_336_MONOMER", "MG_337_MONOMER", "MG_344_MONOMER", "MG_360_MONOMER", "MG_363_MONOMER", "MG_381_MONOMER", "MG_402_MONOMER", "MG_405_MONOMER", "MG_411_MONOMER", "MG_425_MONOMER", "MG_427_MONOMER", "MG_438_MONOMER", "MG_439_MONOMER", "MG_446_MONOMER", "MG_458_MONOMER", "MG_469_MONOMER", "MG_473_MONOMER"]},
  {"name":"MG_044_MONOMER","imports":["MG_002_MONOMER", "MG_007_MONOMER", "MG_022_MONOMER", "MG_024_MONOMER", "MG_026_MONOMER", "MG_027_MONOMER", "MG_028_MONOMER", "MG_043_MONOMER", "MG_044_MONOMER", "MG_050_MONOMER", "MG_054_MONOMER", "MG_055_MONOMER", "MG_056_MONOMER", "MG_069_MONOMER", "MG_070_MONOMER", "MG_088_MONOMER", "MG_094_MONOMER", "MG_097_MONOMER", "MG_105_MONOMER", "MG_125_MONOMER", "MG_141_MONOMER", "MG_147_MONOMER", "MG_148_MONOMER", "MG_153_MONOMER", "MG_169_MONOMER", "MG_180_MONOMER", "MG_182_MONOMER", "MG_183_MONOMER", "MG_239_MONOMER", "MG_241_MONOMER", "MG_242_MONOMER", "MG_244_MONOMER", "MG_275_MONOMER", "MG_281_MONOMER", "MG_282_MONOMER", "MG_293_MONOMER", "MG_317_MONOMER", "MG_336_MONOMER", "MG_337_MONOMER", "MG_344_MONOMER", "MG_360_MONOMER", "MG_363_MONOMER", "MG_380_MONOMER", "MG_381_MONOMER", "MG_398_MONOMER", "MG_402_MONOMER", "MG_405_MONOMER", "MG_406_MONOMER", "MG_424_MONOMER", "MG_425_MONOMER", "MG_427_MONOMER", "MG_428_MONOMER", "MG_438_MONOMER", "MG_439_MONOMER", "MG_446_MONOMER", "MG_458_MONOMER", "MG_469_MONOMER", "MG_473_MONOMER"]},
  {"name":"MG_050_MONOMER","imports":["MG_002_MONOMER", "MG_007_MONOMER", "MG_024_MONOMER", "MG_026_MONOMER", "MG_027_MONOMER", "MG_028_MONOMER", "MG_043_MONOMER", "MG_044_MONOMER", "MG_050_MONOMER", "MG_054_MONOMER", "MG_055_MONOMER", "MG_056_MONOMER", "MG_069_MONOMER", "MG_070_MONOMER", "MG_084_MONOMER", "MG_088_MONOMER", "MG_094_MONOMER", "MG_095_MONOMER", "MG_097_MONOMER", "MG_105_MONOMER", "MG_113_MONOMER", "MG_125_MONOMER", "MG_128_MONOMER", "MG_141_MONOMER", "MG_147_MONOMER", "MG_148_MONOMER", "MG_169_MONOMER", "MG_180_MONOMER", "MG_183_MONOMER", "MG_239_MONOMER", "MG_241_MONOMER", "MG_242_MONOMER", "MG_244_MONOMER", "MG_275_MONOMER", "MG_281_MONOMER", "MG_282_MONOMER", "MG_291_MONOMER", "MG_292_MONOMER", "MG_306_MONOMER", "MG_317_MONOMER", "MG_336_MONOMER", "MG_337_MONOMER", "MG_338_MONOMER", "MG_344_MONOMER", "MG_359_MONOMER", "MG_363_MONOMER", "MG_372_MONOMER", "MG_380_MONOMER", "MG_381_MONOMER", "MG_398_MONOMER", "MG_402_MONOMER", "MG_424_MONOMER", "MG_425_MONOMER", "MG_427_MONOMER", "MG_438_MONOMER", "MG_439_MONOMER", "MG_446_MONOMER", "MG_458_MONOMER", "MG_469_MONOMER", "MG_473_MONOMER", "MG_498_MONOMER"]},
  {"name":"MG_054_MONOMER","imports":["MG_002_MONOMER", "MG_007_MONOMER", "MG_024_MONOMER", "MG_026_MONOMER", "MG_027_MONOMER", "MG_028_MONOMER", "MG_043_MONOMER", "MG_044_MONOMER", "MG_050_MONOMER", "MG_054_MONOMER", "MG_055_MONOMER", "MG_056_MONOMER", "MG_069_MONOMER", "MG_070_MONOMER", "MG_088_MONOMER", "MG_094_MONOMER", "MG_097_MONOMER", "MG_105_MONOMER", "MG_113_MONOMER", "MG_125_MONOMER", "MG_128_MONOMER", "MG_147_MONOMER", "MG_148_MONOMER", "MG_169_MONOMER", "MG_180_MONOMER", "MG_183_MONOMER", "MG_239_MONOMER", "MG_241_MONOMER", "MG_242_MONOMER", "MG_244_MONOMER", "MG_275_MONOMER", "MG_281_MONOMER", "MG_282_MONOMER", "MG_306_MONOMER", "MG_317_MONOMER", "MG_336_MONOMER", "MG_337_MONOMER", "MG_344_MONOMER", "MG_360_MONOMER", "MG_363_MONOMER", "MG_372_MONOMER", "MG_380_MONOMER", "MG_381_MONOMER", "MG_391_MONOMER", "MG_402_MONOMER", "MG_424_MONOMER", "MG_425_MONOMER", "MG_427_MONOMER", "MG_438_MONOMER", "MG_439_MONOMER", "MG_446_MONOMER", "MG_458_MONOMER", "MG_469_MONOMER", "MG_473_MONOMER", "MG_498_MONOMER"]},
  {"name":"MG_055_MONOMER","imports":["MG_002_MONOMER", "MG_007_MONOMER", "MG_011_MONOMER", "MG_022_MONOMER", "MG_024_MONOMER", "MG_026_MONOMER", "MG_027_MONOMER", "MG_028_MONOMER", "MG_043_MONOMER", "MG_044_MONOMER", "MG_050_MONOMER", "MG_054_MONOMER", "MG_055_MONOMER", "MG_056_MONOMER", "MG_069_MONOMER", "MG_070_MONOMER", "MG_084_MONOMER", "MG_088_MONOMER", "MG_094_MONOMER", "MG_097_MONOMER", "MG_105_MONOMER", "MG_113_MONOMER", "MG_125_MONOMER", "MG_128_MONOMER", "MG_141_MONOMER", "MG_147_MONOMER", "MG_148_MONOMER", "MG_153_MONOMER", "MG_169_MONOMER", "MG_180_MONOMER", "MG_183_MONOMER", "MG_239_MONOMER", "MG_241_MONOMER", "MG_242_MONOMER", "MG_244_MONOMER", "MG_275_MONOMER", "MG_281_MONOMER", "MG_282_MONOMER", "MG_291_MONOMER", "MG_292_MONOMER", "MG_306_MONOMER", "MG_317_MONOMER", "MG_335_MONOMER", "MG_336_MONOMER", "MG_337_MONOMER", "MG_338_MONOMER", "MG_344_MONOMER", "MG_360_MONOMER", "MG_363_MONOMER", "MG_372_MONOMER", "MG_380_MONOMER", "MG_381_MONOMER", "MG_391_MONOMER", "MG_398_MONOMER", "MG_402_MONOMER", "MG_424_MONOMER", "MG_425_MONOMER", "MG_427_MONOMER", "MG_428_MONOMER", "MG_438_MONOMER", "MG_439_MONOMER", "MG_446_MONOMER", "MG_458_MONOMER", "MG_469_MONOMER", "MG_473_MONOMER", "MG_498_MONOMER"]},
  {"name":"MG_056_MONOMER","imports":["MG_002_MONOMER", "MG_007_MONOMER", "MG_011_MONOMER", "MG_022_MONOMER", "MG_024_MONOMER", "MG_026_MONOMER", "MG_027_MONOMER", "MG_028_MONOMER", "MG_043_MONOMER", "MG_044_MONOMER", "MG_050_MONOMER", "MG_054_MONOMER", "MG_055_MONOMER", "MG_056_MONOMER", "MG_069_MONOMER", "MG_070_MONOMER", "MG_084_MONOMER", "MG_088_MONOMER", "MG_094_MONOMER", "MG_097_MONOMER", "MG_105_MONOMER", "MG_113_MONOMER", "MG_125_MONOMER", "MG_128_MONOMER", "MG_141_MONOMER", "MG_147_MONOMER", "MG_148_MONOMER", "MG_169_MONOMER", "MG_180_MONOMER", "MG_183_MONOMER", "MG_239_MONOMER", "MG_241_MONOMER", "MG_242_MONOMER", "MG_244_MONOMER", "MG_275_MONOMER", "MG_281_MONOMER", "MG_282_MONOMER", "MG_291_MONOMER", "MG_292_MONOMER", "MG_306_MONOMER", "MG_317_MONOMER", "MG_335_MONOMER", "MG_336_MONOMER", "MG_337_MONOMER", "MG_343_MONOMER", "MG_344_MONOMER", "MG_360_MONOMER", "MG_363_MONOMER", "MG_372_MONOMER", "MG_380_MONOMER", "MG_381_MONOMER", "MG_391_MONOMER", "MG_398_MONOMER", "MG_402_MONOMER", "MG_424_MONOMER", "MG_425_MONOMER", "MG_427_MONOMER", "MG_428_MONOMER", "MG_438_MONOMER", "MG_439_MONOMER", "MG_446_MONOMER", "MG_458_MONOMER", "MG_469_MONOMER", "MG_473_MONOMER", "MG_498_MONOMER"]},
  {"name":"MG_069_MONOMER","imports":["MG_002_MONOMER", "MG_007_MONOMER", "MG_009_MONOMER", "MG_011_MONOMER", "MG_022_MONOMER", "MG_024_MONOMER", "MG_026_MONOMER", "MG_027_MONOMER", "MG_028_MONOMER", "MG_043_MONOMER", "MG_044_MONOMER", "MG_050_MONOMER", "MG_054_MONOMER", "MG_055_MONOMER", "MG_056_MONOMER", "MG_069_MONOMER", "MG_070_MONOMER", "MG_084_MONOMER", "MG_088_MONOMER", "MG_094_MONOMER", "MG_097_MONOMER", "MG_105_MONOMER", "MG_113_MONOMER", "MG_125_MONOMER", "MG_128_MONOMER", "MG_141_MONOMER", "MG_147_MONOMER", "MG_148_MONOMER", "MG_153_MONOMER", "MG_169_MONOMER", "MG_180_MONOMER", "MG_183_MONOMER", "MG_205_MONOMER", "MG_239_MONOMER", "MG_241_MONOMER", "MG_242_MONOMER", "MG_244_MONOMER", "MG_275_MONOMER", "MG_281_MONOMER", "MG_282_MONOMER", "MG_291_MONOMER", "MG_292_MONOMER", "MG_306_MONOMER", "MG_317_MONOMER", "MG_335_MONOMER", "MG_336_MONOMER", "MG_337_MONOMER", "MG_338_MONOMER", "MG_343_MONOMER", "MG_344_MONOMER", "MG_360_MONOMER", "MG_363_MONOMER", "MG_372_MONOMER", "MG_380_MONOMER", "MG_381_MONOMER", "MG_391_MONOMER", "MG_398_MONOMER", "MG_402_MONOMER", "MG_424_MONOMER", "MG_425_MONOMER", "MG_427_MONOMER", "MG_428_MONOMER", "MG_438_MONOMER", "MG_439_MONOMER", "MG_446_MONOMER", "MG_458_MONOMER", "MG_469_MONOMER", "MG_473_MONOMER", "MG_498_MONOMER"]},
  {"name":"MG_070_MONOMER","imports":["MG_002_MONOMER", "MG_007_MONOMER", "MG_011_MONOMER", "MG_022_MONOMER", "MG_024_MONOMER", "MG_026_MONOMER", "MG_027_MONOMER", "MG_028_MONOMER", "MG_043_MONOMER", "MG_044_MONOMER", "MG_050_MONOMER", "MG_054_MONOMER", "MG_055_MONOMER", "MG_056_MONOMER", "MG_069_MONOMER", "MG_070_MONOMER", "MG_084_MONOMER", "MG_088_MONOMER", "MG_094_MONOMER", "MG_095_MONOMER", "MG_097_MONOMER", "MG_105_MONOMER", "MG_113_MONOMER", "MG_125_MONOMER", "MG_128_MONOMER", "MG_141_MONOMER", "MG_147_MONOMER", "MG_148_MONOMER", "MG_153_MONOMER", "MG_169_MONOMER", "MG_180_MONOMER", "MG_183_MONOMER", "MG_239_MONOMER", "MG_241_MONOMER", "MG_242_MONOMER", "MG_244_MONOMER", "MG_268_MONOMER", "MG_275_MONOMER", "MG_281_MONOMER", "MG_282_MONOMER", "MG_291_MONOMER", "MG_292_MONOMER", "MG_306_MONOMER", "MG_317_MONOMER", "MG_335_MONOMER", "MG_336_MONOMER", "MG_337_MONOMER", "MG_338_MONOMER", "MG_343_MONOMER", "MG_344_MONOMER", "MG_360_MONOMER", "MG_363_MONOMER", "MG_372_MONOMER", "MG_380_MONOMER", "MG_381_MONOMER", "MG_391_MONOMER", "MG_398_MONOMER", "MG_402_MONOMER", "MG_424_MONOMER", "MG_425_MONOMER", "MG_427_MONOMER", "MG_428_MONOMER", "MG_438_MONOMER", "MG_439_MONOMER", "MG_446_MONOMER", "MG_458_MONOMER", "MG_469_MONOMER", "MG_473_MONOMER", "MG_498_MONOMER"]},
  {"name":"MG_072_MONOMER","imports":["MG_072_MONOMER", "MG_390_MONOMER"]},
  {"name":"MG_076_MONOMER","imports":["MG_076_MONOMER", "MG_306_MONOMER", "MG_467_MONOMER"]},
  {"name":"MG_078_MONOMER","imports":["MG_078_MONOMER", "MG_462_MONOMER"]},
  {"name":"MG_083_MONOMER","imports":["MG_083_MONOMER", "MG_084_MONOMER", "MG_306_MONOMER"]},
  {"name":"MG_084_MONOMER","imports":["MG_024_MONOMER", "MG_027_MONOMER", "MG_028_MONOMER", "MG_050_MONOMER", "MG_055_MONOMER", "MG_056_MONOMER", "MG_069_MONOMER", "MG_070_MONOMER", "MG_083_MONOMER", "MG_084_MONOMER", "MG_088_MONOMER", "MG_094_MONOMER", "MG_097_MONOMER", "MG_105_MONOMER", "MG_125_MONOMER", "MG_183_MONOMER", "MG_217_MONOMER", "MG_239_MONOMER", "MG_244_MONOMER", "MG_275_MONOMER", "MG_281_MONOMER", "MG_282_MONOMER", "MG_306_MONOMER", "MG_336_MONOMER", "MG_337_MONOMER", "MG_338_MONOMER", "MG_359_MONOMER", "MG_363_MONOMER", "MG_380_MONOMER", "MG_424_MONOMER", "MG_425_MONOMER", "MG_427_MONOMER", "MG_439_MONOMER", "MG_469_MONOMER"]},
  {"name":"MG_088_MONOMER","imports":["MG_002_MONOMER", "MG_007_MONOMER", "MG_011_MONOMER", "MG_022_MONOMER", "MG_024_MONOMER", "MG_026_MONOMER", "MG_027_MONOMER", "MG_028_MONOMER", "MG_043_MONOMER", "MG_044_MONOMER", "MG_050_MONOMER", "MG_054_MONOMER", "MG_055_MONOMER", "MG_056_MONOMER", "MG_069_MONOMER", "MG_070_MONOMER", "MG_084_MONOMER", "MG_088_MONOMER", "MG_094_MONOMER", "MG_095_MONOMER", "MG_097_MONOMER", "MG_105_MONOMER", "MG_113_MONOMER", "MG_125_MONOMER", "MG_128_MONOMER", "MG_141_MONOMER", "MG_147_MONOMER", "MG_148_MONOMER", "MG_153_MONOMER", "MG_169_MONOMER", "MG_180_MONOMER", "MG_182_MONOMER", "MG_183_MONOMER", "MG_239_MONOMER", "MG_241_MONOMER", "MG_242_MONOMER", "MG_244_MONOMER", "MG_275_MONOMER", "MG_281_MONOMER", "MG_282_MONOMER", "MG_291_MONOMER", "MG_292_MONOMER", "MG_306_MONOMER", "MG_317_MONOMER", "MG_335_MONOMER", "MG_336_MONOMER", "MG_337_MONOMER", "MG_338_MONOMER", "MG_343_MONOMER", "MG_344_MONOMER", "MG_359_MONOMER", "MG_360_MONOMER", "MG_363_MONOMER", "MG_372_MONOMER", "MG_380_MONOMER", "MG_381_MONOMER", "MG_391_MONOMER", "MG_398_MONOMER", "MG_402_MONOMER", "MG_424_MONOMER", "MG_425_MONOMER", "MG_427_MONOMER", "MG_428_MONOMER", "MG_438_MONOMER", "MG_439_MONOMER", "MG_446_MONOMER", "MG_458_MONOMER", "MG_469_MONOMER", "MG_473_MONOMER", "MG_498_MONOMER"]},
  {"name":"MG_089_MONOMER","imports":["MG_089_MONOMER", "MG_090_MONOMER"]},
  {"name":"MG_090_MONOMER","imports":["MG_089_MONOMER", "MG_090_MONOMER", "MG_405_MONOMER"]},
  {"name":"MG_094_MONOMER","imports":["MG_002_MONOMER", "MG_007_MONOMER", "MG_009_MONOMER", "MG_011_MONOMER", "MG_024_MONOMER", "MG_026_MONOMER", "MG_027_MONOMER", "MG_028_MONOMER", "MG_043_MONOMER", "MG_044_MONOMER", "MG_050_MONOMER", "MG_054_MONOMER", "MG_055_MONOMER", "MG_056_MONOMER", "MG_069_MONOMER", "MG_070_MONOMER", "MG_084_MONOMER", "MG_088_MONOMER", "MG_094_MONOMER", "MG_097_MONOMER", "MG_105_MONOMER", "MG_113_MONOMER", "MG_125_MONOMER", "MG_128_MONOMER", "MG_141_MONOMER", "MG_147_MONOMER", "MG_148_MONOMER", "MG_153_MONOMER", "MG_169_MONOMER", "MG_180_MONOMER", "MG_183_MONOMER", "MG_239_MONOMER", "MG_241_MONOMER", "MG_242_MONOMER", "MG_244_MONOMER", "MG_275_MONOMER", "MG_281_MONOMER", "MG_282_MONOMER", "MG_291_MONOMER", "MG_292_MONOMER", "MG_306_MONOMER", "MG_317_MONOMER", "MG_336_MONOMER", "MG_337_MONOMER", "MG_343_MONOMER", "MG_344_MONOMER", "MG_360_MONOMER", "MG_363_MONOMER", "MG_372_MONOMER", "MG_380_MONOMER", "MG_381_MONOMER", "MG_391_MONOMER", "MG_398_MONOMER", "MG_402_MONOMER", "MG_411_MONOMER", "MG_418_MONOMER", "MG_424_MONOMER", "MG_425_MONOMER", "MG_427_MONOMER", "MG_428_MONOMER", "MG_438_MONOMER", "MG_439_MONOMER", "MG_446_MONOMER", "MG_458_MONOMER", "MG_469_MONOMER", "MG_473_MONOMER", "MG_498_MONOMER"]},
  {"name":"MG_095_MONOMER","imports":["MG_024_MONOMER", "MG_050_MONOMER", "MG_070_MONOMER", "MG_088_MONOMER", "MG_095_MONOMER", "MG_097_MONOMER", "MG_183_MONOMER", "MG_381_MONOMER"]},
  {"name":"MG_097_MONOMER","imports":["MG_002_MONOMER", "MG_007_MONOMER", "MG_009_MONOMER", "MG_011_MONOMER", "MG_022_MONOMER", "MG_024_MONOMER", "MG_026_MONOMER", "MG_027_MONOMER", "MG_028_MONOMER", "MG_043_MONOMER", "MG_044_MONOMER", "MG_050_MONOMER", "MG_054_MONOMER", "MG_055_MONOMER", "MG_056_MONOMER", "MG_069_MONOMER", "MG_070_MONOMER", "MG_084_MONOMER", "MG_088_MONOMER", "MG_094_MONOMER", "MG_095_MONOMER", "MG_097_MONOMER", "MG_105_MONOMER", "MG_113_MONOMER", "MG_125_MONOMER", "MG_128_MONOMER", "MG_141_MONOMER", "MG_147_MONOMER", "MG_148_MONOMER", "MG_153_MONOMER", "MG_169_MONOMER", "MG_180_MONOMER", "MG_183_MONOMER", "MG_205_MONOMER", "MG_239_MONOMER", "MG_241_MONOMER", "MG_242_MONOMER", "MG_244_MONOMER", "MG_275_MONOMER", "MG_281_MONOMER", "MG_282_MONOMER", "MG_291_MONOMER", "MG_292_MONOMER", "MG_306_MONOMER", "MG_317_MONOMER", "MG_335_MONOMER", "MG_336_MONOMER", "MG_337_MONOMER", "MG_338_MONOMER", "MG_343_MONOMER", "MG_344_MONOMER", "MG_359_MONOMER", "MG_360_MONOMER", "MG_363_MONOMER", "MG_372_MONOMER", "MG_380_MONOMER", "MG_381_MONOMER", "MG_391_MONOMER", "MG_398_MONOMER", "MG_402_MONOMER", "MG_418_MONOMER", "MG_424_MONOMER", "MG_425_MONOMER", "MG_427_MONOMER", "MG_428_MONOMER", "MG_438_MONOMER", "MG_439_MONOMER", "MG_446_MONOMER", "MG_458_MONOMER", "MG_469_MONOMER", "MG_473_MONOMER", "MG_498_MONOMER"]},
  {"name":"MG_098_MONOMER","imports":["MG_098_MONOMER", "MG_150_MONOMER"]},
  {"name":"MG_105_MONOMER","imports":["MG_007_MONOMER", "MG_024_MONOMER", "MG_026_MONOMER", "MG_027_MONOMER", "MG_028_MONOMER", "MG_043_MONOMER", "MG_044_MONOMER", "MG_050_MONOMER", "MG_054_MONOMER", "MG_055_MONOMER", "MG_056_MONOMER", "MG_069_MONOMER", "MG_070_MONOMER", "MG_084_MONOMER", "MG_088_MONOMER", "MG_094_MONOMER", "MG_097_MONOMER", "MG_105_MONOMER", "MG_125_MONOMER", "MG_128_MONOMER", "MG_141_MONOMER", "MG_169_MONOMER", "MG_183_MONOMER", "MG_239_MONOMER", "MG_242_MONOMER", "MG_244_MONOMER", "MG_275_MONOMER", "MG_281_MONOMER", "MG_282_MONOMER", "MG_306_MONOMER", "MG_336_MONOMER", "MG_337_MONOMER", "MG_338_MONOMER", "MG_344_MONOMER", "MG_363_MONOMER", "MG_372_MONOMER", "MG_380_MONOMER", "MG_391_MONOMER", "MG_402_MONOMER", "MG_424_MONOMER", "MG_425_MONOMER", "MG_427_MONOMER", "MG_438_MONOMER", "MG_439_MONOMER", "MG_446_MONOMER", "MG_469_MONOMER", "MG_473_MONOMER"]},
  {"name":"MG_113_MONOMER","imports":["MG_007_MONOMER", "MG_024_MONOMER", "MG_027_MONOMER", "MG_028_MONOMER", "MG_050_MONOMER", "MG_054_MONOMER", "MG_055_MONOMER", "MG_056_MONOMER", "MG_069_MONOMER", "MG_070_MONOMER", "MG_088_MONOMER", "MG_094_MONOMER", "MG_097_MONOMER", "MG_113_MONOMER", "MG_125_MONOMER", "MG_147_MONOMER", "MG_148_MONOMER", "MG_239_MONOMER", "MG_242_MONOMER", "MG_244_MONOMER", "MG_281_MONOMER", "MG_282_MONOMER", "MG_306_MONOMER", "MG_336_MONOMER", "MG_337_MONOMER", "MG_363_MONOMER", "MG_381_MONOMER", "MG_402_MONOMER", "MG_425_MONOMER", "MG_427_MONOMER", "MG_438_MONOMER", "MG_439_MONOMER"]},
  {"name":"MG_124_MONOMER","imports":["MG_124_MONOMER", "MG_338_MONOMER"]},
  {"name":"MG_125_MONOMER","imports":["MG_002_MONOMER", "MG_007_MONOMER", "MG_009_MONOMER", "MG_011_MONOMER", "MG_022_MONOMER", "MG_024_MONOMER", "MG_026_MONOMER", "MG_027_MONOMER", "MG_028_MONOMER", "MG_043_MONOMER", "MG_044_MONOMER", "MG_050_MONOMER", "MG_054_MONOMER", "MG_055_MONOMER", "MG_056_MONOMER", "MG_069_MONOMER", "MG_070_MONOMER", "MG_084_MONOMER", "MG_088_MONOMER", "MG_094_MONOMER", "MG_097_MONOMER", "MG_105_MONOMER", "MG_113_MONOMER", "MG_125_MONOMER", "MG_128_MONOMER", "MG_141_MONOMER", "MG_147_MONOMER", "MG_148_MONOMER", "MG_153_MONOMER", "MG_169_MONOMER", "MG_180_MONOMER", "MG_183_MONOMER", "MG_205_MONOMER", "MG_239_MONOMER", "MG_241_MONOMER", "MG_242_MONOMER", "MG_244_MONOMER", "MG_275_MONOMER", "MG_281_MONOMER", "MG_282_MONOMER", "MG_291_MONOMER", "MG_292_MONOMER", "MG_306_MONOMER", "MG_317_MONOMER", "MG_335_MONOMER", "MG_336_MONOMER", "MG_337_MONOMER", "MG_338_MONOMER", "MG_343_MONOMER", "MG_344_MONOMER", "MG_359_MONOMER", "MG_360_MONOMER", "MG_363_MONOMER", "MG_372_MONOMER", "MG_380_MONOMER", "MG_381_MONOMER", "MG_391_MONOMER", "MG_398_MONOMER", "MG_402_MONOMER", "MG_418_MONOMER", "MG_424_MONOMER", "MG_425_MONOMER", "MG_427_MONOMER", "MG_428_MONOMER", "MG_438_MONOMER", "MG_439_MONOMER", "MG_446_MONOMER", "MG_458_MONOMER", "MG_469_MONOMER", "MG_473_MONOMER", "MG_498_MONOMER"]},
  {"name":"MG_128_MONOMER","imports":["MG_002_MONOMER", "MG_007_MONOMER", "MG_024_MONOMER", "MG_026_MONOMER", "MG_027_MONOMER", "MG_028_MONOMER", "MG_050_MONOMER", "MG_054_MONOMER", "MG_055_MONOMER", "MG_056_MONOMER", "MG_069_MONOMER", "MG_070_MONOMER", "MG_088_MONOMER", "MG_094_MONOMER", "MG_097_MONOMER", "MG_105_MONOMER", "MG_125_MONOMER", "MG_128_MONOMER", "MG_147_MONOMER", "MG_148_MONOMER", "MG_239_MONOMER", "MG_242_MONOMER", "MG_244_MONOMER", "MG_281_MONOMER", "MG_282_MONOMER", "MG_306_MONOMER", "MG_336_MONOMER", "MG_337_MONOMER", "MG_338_MONOMER", "MG_344_MONOMER", "MG_363_MONOMER", "MG_372_MONOMER", "MG_402_MONOMER", "MG_424_MONOMER", "MG_425_MONOMER", "MG_427_MONOMER", "MG_438_MONOMER", "MG_439_MONOMER", "MG_446_MONOMER", "MG_469_MONOMER", "MG_498_MONOMER"]},
  {"name":"MG_134_MONOMER","imports":["MG_134_MONOMER", "MG_143_MONOMER", "MG_264_MONOMER"]},
  {"name":"MG_138_MONOMER","imports":["MG_138_MONOMER", "MG_466_MONOMER"]},
  {"name":"MG_141_MONOMER","imports":["MG_022_MONOMER", "MG_024_MONOMER", "MG_026_MONOMER", "MG_027_MONOMER", "MG_028_MONOMER", "MG_043_MONOMER", "MG_044_MONOMER", "MG_050_MONOMER", "MG_055_MONOMER", "MG_056_MONOMER", "MG_069_MONOMER", "MG_070_MONOMER", "MG_088_MONOMER", "MG_094_MONOMER", "MG_097_MONOMER", "MG_105_MONOMER", "MG_125_MONOMER", "MG_141_MONOMER", "MG_153_MONOMER", "MG_169_MONOMER", "MG_239_MONOMER", "MG_244_MONOMER", "MG_275_MONOMER", "MG_281_MONOMER", "MG_282_MONOMER", "MG_336_MONOMER", "MG_337_MONOMER", "MG_338_MONOMER", "MG_360_MONOMER", "MG_363_MONOMER", "MG_402_MONOMER", "MG_405_MONOMER", "MG_439_MONOMER", "MG_469_MONOMER"]},
  {"name":"MG_143_MONOMER","imports":["MG_134_MONOMER", "MG_143_MONOMER", "MG_264_MONOMER"]},
  {"name":"MG_147_MONOMER","imports":["MG_002_MONOMER", "MG_007_MONOMER", "MG_009_MONOMER", "MG_011_MONOMER", "MG_024_MONOMER", "MG_026_MONOMER", "MG_027_MONOMER", "MG_028_MONOMER", "MG_043_MONOMER", "MG_044_MONOMER", "MG_050_MONOMER", "MG_054_MONOMER", "MG_055_MONOMER", "MG_056_MONOMER", "MG_069_MONOMER", "MG_070_MONOMER", "MG_088_MONOMER", "MG_094_MONOMER", "MG_097_MONOMER", "MG_113_MONOMER", "MG_125_MONOMER", "MG_128_MONOMER", "MG_147_MONOMER", "MG_148_MONOMER", "MG_169_MONOMER", "MG_180_MONOMER", "MG_183_MONOMER", "MG_239_MONOMER", "MG_242_MONOMER", "MG_244_MONOMER", "MG_281_MONOMER", "MG_282_MONOMER", "MG_306_MONOMER", "MG_335_MONOMER", "MG_336_MONOMER", "MG_337_MONOMER", "MG_344_MONOMER", "MG_363_MONOMER", "MG_372_MONOMER", "MG_381_MONOMER", "MG_391_MONOMER", "MG_398_MONOMER", "MG_402_MONOMER", "MG_418_MONOMER", "MG_424_MONOMER", "MG_425_MONOMER", "MG_427_MONOMER", "MG_428_MONOMER", "MG_438_MONOMER", "MG_439_MONOMER", "MG_446_MONOMER", "MG_458_MONOMER", "MG_469_MONOMER", "MG_473_MONOMER"]},
  {"name":"MG_148_MONOMER","imports":["MG_002_MONOMER", "MG_007_MONOMER", "MG_009_MONOMER", "MG_011_MONOMER", "MG_024_MONOMER", "MG_026_MONOMER", "MG_027_MONOMER", "MG_028_MONOMER", "MG_043_MONOMER", "MG_044_MONOMER", "MG_050_MONOMER", "MG_054_MONOMER", "MG_055_MONOMER", "MG_056_MONOMER", "MG_069_MONOMER", "MG_070_MONOMER", "MG_088_MONOMER", "MG_094_MONOMER", "MG_097_MONOMER", "MG_113_MONOMER", "MG_125_MONOMER", "MG_128_MONOMER", "MG_147_MONOMER", "MG_148_MONOMER", "MG_180_MONOMER", "MG_183_MONOMER", "MG_239_MONOMER", "MG_242_MONOMER", "MG_244_MONOMER", "MG_281_MONOMER", "MG_282_MONOMER", "MG_291_MONOMER", "MG_292_MONOMER", "MG_306_MONOMER", "MG_336_MONOMER", "MG_337_MONOMER", "MG_344_MONOMER", "MG_363_MONOMER", "MG_372_MONOMER", "MG_381_MONOMER", "MG_398_MONOMER", "MG_402_MONOMER", "MG_418_MONOMER", "MG_424_MONOMER", "MG_425_MONOMER", "MG_427_MONOMER", "MG_428_MONOMER", "MG_438_MONOMER", "MG_439_MONOMER", "MG_446_MONOMER", "MG_458_MONOMER", "MG_469_MONOMER", "MG_473_MONOMER"]},
  {"name":"MG_150_MONOMER","imports":["MG_098_MONOMER", "MG_150_MONOMER"]},
  {"name":"MG_153_MONOMER","imports":["MG_002_MONOMER", "MG_022_MONOMER", "MG_024_MONOMER", "MG_027_MONOMER", "MG_028_MONOMER", "MG_043_MONOMER", "MG_044_MONOMER", "MG_055_MONOMER", "MG_069_MONOMER", "MG_070_MONOMER", "MG_088_MONOMER", "MG_094_MONOMER", "MG_097_MONOMER", "MG_125_MONOMER", "MG_141_MONOMER", "MG_153_MONOMER", "MG_239_MONOMER", "MG_275_MONOMER", "MG_281_MONOMER", "MG_282_MONOMER", "MG_336_MONOMER", "MG_337_MONOMER", "MG_360_MONOMER", "MG_363_MONOMER", "MG_402_MONOMER", "MG_439_MONOMER", "MG_469_MONOMER", "MG_473_MONOMER"]},
  {"name":"MG_156_MONOMER","imports":["MG_156_MONOMER", "MG_243_MONOMER"]},
  {"name":"MG_159_MONOMER","imports":["MG_159_MONOMER", "MG_160_MONOMER", "MG_161_MONOMER", "MG_162_MONOMER", "MG_163_MONOMER", "MG_167_MONOMER"]},
  {"name":"MG_160_MONOMER","imports":["MG_159_MONOMER", "MG_160_MONOMER", "MG_161_MONOMER", "MG_162_MONOMER", "MG_163_MONOMER", "MG_167_MONOMER"]},
  {"name":"MG_161_MONOMER","imports":["MG_159_MONOMER", "MG_160_MONOMER", "MG_161_MONOMER", "MG_162_MONOMER", "MG_163_MONOMER", "MG_165_MONOMER", "MG_167_MONOMER"]},
  {"name":"MG_162_MONOMER","imports":["MG_159_MONOMER", "MG_160_MONOMER", "MG_161_MONOMER", "MG_162_MONOMER", "MG_163_MONOMER", "MG_167_MONOMER", "MG_168_MONOMER"]},
  {"name":"MG_163_MONOMER","imports":["MG_159_MONOMER", "MG_160_MONOMER", "MG_161_MONOMER", "MG_162_MONOMER", "MG_163_MONOMER", "MG_165_MONOMER", "MG_167_MONOMER"]},
  {"name":"MG_164_MONOMER","imports":["MG_164_MONOMER", "MG_166_MONOMER"]},
  {"name":"MG_165_MONOMER","imports":["MG_161_MONOMER", "MG_163_MONOMER", "MG_165_MONOMER", "MG_166_MONOMER", "MG_167_MONOMER"]},
  {"name":"MG_166_MONOMER","imports":["MG_164_MONOMER", "MG_165_MONOMER", "MG_166_MONOMER"]},
  {"name":"MG_167_MONOMER","imports":["MG_159_MONOMER", "MG_160_MONOMER", "MG_161_MONOMER", "MG_162_MONOMER", "MG_163_MONOMER", "MG_165_MONOMER", "MG_167_MONOMER"]},
  {"name":"MG_168_MONOMER","imports":["MG_162_MONOMER", "MG_168_MONOMER"]},
  {"name":"MG_169_MONOMER","imports":["MG_007_MONOMER", "MG_026_MONOMER", "MG_027_MONOMER", "MG_028_MONOMER", "MG_043_MONOMER", "MG_044_MONOMER", "MG_050_MONOMER", "MG_054_MONOMER", "MG_055_MONOMER", "MG_056_MONOMER", "MG_069_MONOMER", "MG_070_MONOMER", "MG_088_MONOMER", "MG_094_MONOMER", "MG_097_MONOMER", "MG_105_MONOMER", "MG_125_MONOMER", "MG_141_MONOMER", "MG_147_MONOMER", "MG_169_MONOMER", "MG_180_MONOMER", "MG_239_MONOMER", "MG_244_MONOMER", "MG_275_MONOMER", "MG_281_MONOMER", "MG_282_MONOMER", "MG_336_MONOMER", "MG_337_MONOMER", "MG_344_MONOMER", "MG_363_MONOMER", "MG_380_MONOMER", "MG_381_MONOMER", "MG_424_MONOMER", "MG_425_MONOMER", "MG_427_MONOMER", "MG_438_MONOMER", "MG_439_MONOMER"]},
  {"name":"MG_170_MONOMER","imports":["MG_170_MONOMER", "MG_174_MONOMER"]},
  {"name":"MG_174_MONOMER","imports":["MG_170_MONOMER", "MG_174_MONOMER"]},
  {"name":"MG_180_MONOMER","imports":["MG_007_MONOMER", "MG_011_MONOMER", "MG_024_MONOMER", "MG_026_MONOMER", "MG_027_MONOMER", "MG_028_MONOMER", "MG_043_MONOMER", "MG_044_MONOMER", "MG_050_MONOMER", "MG_054_MONOMER", "MG_055_MONOMER", "MG_056_MONOMER", "MG_069_MONOMER", "MG_070_MONOMER", "MG_088_MONOMER", "MG_094_MONOMER", "MG_097_MONOMER", "MG_125_MONOMER", "MG_147_MONOMER", "MG_148_MONOMER", "MG_169_MONOMER", "MG_180_MONOMER", "MG_181_MONOMER", "MG_183_MONOMER", "MG_239_MONOMER", "MG_242_MONOMER", "MG_244_MONOMER", "MG_268_MONOMER", "MG_281_MONOMER", "MG_282_MONOMER", "MG_306_MONOMER", "MG_317_MONOMER", "MG_336_MONOMER", "MG_337_MONOMER", "MG_344_MONOMER", "MG_380_MONOMER", "MG_381_MONOMER", "MG_402_MONOMER", "MG_424_MONOMER", "MG_425_MONOMER", "MG_427_MONOMER", "MG_438_MONOMER", "MG_439_MONOMER", "MG_446_MONOMER", "MG_469_MONOMER"]},
  {"name":"MG_181_MONOMER","imports":["MG_180_MONOMER", "MG_181_MONOMER"]},
  {"name":"MG_182_MONOMER","imports":["MG_022_MONOMER", "MG_024_MONOMER", "MG_044_MONOMER", "MG_088_MONOMER", "MG_182_MONOMER"]},
  {"name":"MG_183_MONOMER","imports":["MG_002_MONOMER", "MG_007_MONOMER", "MG_022_MONOMER", "MG_024_MONOMER", "MG_027_MONOMER", "MG_028_MONOMER", "MG_043_MONOMER", "MG_044_MONOMER", "MG_050_MONOMER", "MG_054_MONOMER", "MG_055_MONOMER", "MG_056_MONOMER", "MG_069_MONOMER", "MG_070_MONOMER", "MG_084_MONOMER", "MG_088_MONOMER", "MG_094_MONOMER", "MG_095_MONOMER", "MG_097_MONOMER", "MG_105_MONOMER", "MG_125_MONOMER", "MG_147_MONOMER", "MG_148_MONOMER", "MG_180_MONOMER", "MG_183_MONOMER", "MG_239_MONOMER", "MG_241_MONOMER", "MG_242_MONOMER", "MG_244_MONOMER", "MG_281_MONOMER", "MG_282_MONOMER", "MG_291_MONOMER", "MG_317_MONOMER", "MG_336_MONOMER", "MG_337_MONOMER", "MG_344_MONOMER", "MG_360_MONOMER", "MG_380_MONOMER", "MG_381_MONOMER", "MG_391_MONOMER", "MG_398_MONOMER", "MG_402_MONOMER", "MG_424_MONOMER", "MG_425_MONOMER", "MG_427_MONOMER", "MG_438_MONOMER", "MG_439_MONOMER", "MG_446_MONOMER", "MG_469_MONOMER", "MG_473_MONOMER", "MG_498_MONOMER"]},
  {"name":"MG_190_MONOMER","imports":["MG_190_MONOMER", "MG_329_MONOMER", "MG_330_MONOMER"]},
  {"name":"MG_192_MONOMER","imports":["MG_192_MONOMER", "MG_194_MONOMER", "MG_195_MONOMER"]},
  {"name":"MG_194_MONOMER","imports":["MG_192_MONOMER", "MG_194_MONOMER"]},
  {"name":"MG_195_MONOMER","imports":["MG_192_MONOMER", "MG_195_MONOMER"]},
  {"name":"MG_205_MONOMER","imports":["MG_007_MONOMER", "MG_027_MONOMER", "MG_028_MONOMER", "MG_069_MONOMER", "MG_097_MONOMER", "MG_125_MONOMER", "MG_205_MONOMER", "MG_207_MONOMER", "MG_239_MONOMER", "MG_281_MONOMER", "MG_282_MONOMER", "MG_336_MONOMER", "MG_381_MONOMER", "MG_424_MONOMER", "MG_425_MONOMER", "MG_427_MONOMER", "MG_439_MONOMER", "MG_469_MONOMER", "MG_473_MONOMER"]},
  {"name":"MG_207_MONOMER","imports":["MG_205_MONOMER", "MG_207_MONOMER"]},
  {"name":"MG_214_MONOMER","imports":["MG_214_MONOMER", "MG_498_MONOMER"]},
  {"name":"MG_217_MONOMER","imports":["MG_084_MONOMER", "MG_217_MONOMER", "MG_338_MONOMER"]},
  {"name":"MG_239_MONOMER","imports":["MG_002_MONOMER", "MG_007_MONOMER", "MG_009_MONOMER", "MG_011_MONOMER", "MG_022_MONOMER", "MG_024_MONOMER", "MG_026_MONOMER", "MG_027_MONOMER", "MG_028_MONOMER", "MG_043_MONOMER", "MG_044_MONOMER", "MG_050_MONOMER", "MG_054_MONOMER", "MG_055_MONOMER", "MG_056_MONOMER", "MG_069_MONOMER", "MG_070_MONOMER", "MG_084_MONOMER", "MG_088_MONOMER", "MG_094_MONOMER", "MG_097_MONOMER", "MG_105_MONOMER", "MG_113_MONOMER", "MG_125_MONOMER", "MG_128_MONOMER", "MG_141_MONOMER", "MG_147_MONOMER", "MG_148_MONOMER", "MG_153_MONOMER", "MG_169_MONOMER", "MG_180_MONOMER", "MG_183_MONOMER", "MG_205_MONOMER", "MG_239_MONOMER", "MG_241_MONOMER", "MG_242_MONOMER", "MG_244_MONOMER", "MG_275_MONOMER", "MG_281_MONOMER", "MG_282_MONOMER", "MG_291_MONOMER", "MG_292_MONOMER", "MG_306_MONOMER", "MG_317_MONOMER", "MG_335_MONOMER", "MG_336_MONOMER", "MG_337_MONOMER", "MG_338_MONOMER", "MG_343_MONOMER", "MG_344_MONOMER", "MG_359_MONOMER", "MG_360_MONOMER", "MG_363_MONOMER", "MG_372_MONOMER", "MG_380_MONOMER", "MG_381_MONOMER", "MG_391_MONOMER", "MG_398_MONOMER", "MG_402_MONOMER", "MG_418_MONOMER", "MG_424_MONOMER", "MG_425_MONOMER", "MG_427_MONOMER", "MG_428_MONOMER", "MG_438_MONOMER", "MG_439_MONOMER", "MG_446_MONOMER", "MG_458_MONOMER", "MG_469_MONOMER", "MG_473_MONOMER", "MG_498_MONOMER"]},
  {"name":"MG_241_MONOMER","imports":["MG_024_MONOMER", "MG_027_MONOMER", "MG_028_MONOMER", "MG_043_MONOMER", "MG_044_MONOMER", "MG_050_MONOMER", "MG_054_MONOMER", "MG_055_MONOMER", "MG_056_MONOMER", "MG_069_MONOMER", "MG_070_MONOMER", "MG_088_MONOMER", "MG_094_MONOMER", "MG_097_MONOMER", "MG_125_MONOMER", "MG_183_MONOMER", "MG_239_MONOMER", "MG_241_MONOMER", "MG_242_MONOMER", "MG_243_MONOMER", "MG_244_MONOMER", "MG_281_MONOMER", "MG_282_MONOMER", "MG_317_MONOMER", "MG_336_MONOMER", "MG_337_MONOMER", "MG_402_MONOMER", "MG_425_MONOMER", "MG_427_MONOMER", "MG_439_MONOMER", "MG_469_MONOMER"]},
  {"name":"MG_242_MONOMER","imports":["MG_002_MONOMER", "MG_007_MONOMER", "MG_022_MONOMER", "MG_024_MONOMER", "MG_026_MONOMER", "MG_027_MONOMER", "MG_028_MONOMER", "MG_043_MONOMER", "MG_044_MONOMER", "MG_050_MONOMER", "MG_054_MONOMER", "MG_055_MONOMER", "MG_056_MONOMER", "MG_069_MONOMER", "MG_070_MONOMER", "MG_088_MONOMER", "MG_094_MONOMER", "MG_097_MONOMER", "MG_105_MONOMER", "MG_113_MONOMER", "MG_125_MONOMER", "MG_128_MONOMER", "MG_147_MONOMER", "MG_148_MONOMER", "MG_180_MONOMER", "MG_183_MONOMER", "MG_239_MONOMER", "MG_241_MONOMER", "MG_242_MONOMER", "MG_244_MONOMER", "MG_281_MONOMER", "MG_282_MONOMER", "MG_306_MONOMER", "MG_317_MONOMER", "MG_336_MONOMER", "MG_337_MONOMER", "MG_344_MONOMER", "MG_363_MONOMER", "MG_380_MONOMER", "MG_402_MONOMER", "MG_424_MONOMER", "MG_425_MONOMER", "MG_427_MONOMER", "MG_438_MONOMER", "MG_439_MONOMER", "MG_446_MONOMER", "MG_469_MONOMER", "MG_498_MONOMER"]},
  {"name":"MG_243_MONOMER","imports":["MG_156_MONOMER", "MG_241_MONOMER", "MG_243_MONOMER", "MG_244_MONOMER", "MG_469_MONOMER"]},
  {"name":"MG_244_MONOMER","imports":["MG_002_MONOMER", "MG_007_MONOMER", "MG_011_MONOMER", "MG_022_MONOMER", "MG_024_MONOMER", "MG_026_MONOMER", "MG_027_MONOMER", "MG_028_MONOMER", "MG_043_MONOMER", "MG_044_MONOMER", "MG_050_MONOMER", "MG_054_MONOMER", "MG_055_MONOMER", "MG_056_MONOMER", "MG_069_MONOMER", "MG_070_MONOMER", "MG_084_MONOMER", "MG_088_MONOMER", "MG_094_MONOMER", "MG_097_MONOMER", "MG_105_MONOMER", "MG_113_MONOMER", "MG_125_MONOMER", "MG_128_MONOMER", "MG_141_MONOMER", "MG_147_MONOMER", "MG_148_MONOMER", "MG_169_MONOMER", "MG_180_MONOMER", "MG_183_MONOMER", "MG_239_MONOMER", "MG_241_MONOMER", "MG_242_MONOMER", "MG_243_MONOMER", "MG_244_MONOMER", "MG_281_MONOMER", "MG_282_MONOMER", "MG_291_MONOMER", "MG_306_MONOMER", "MG_317_MONOMER", "MG_336_MONOMER", "MG_337_MONOMER", "MG_344_MONOMER", "MG_360_MONOMER", "MG_363_MONOMER", "MG_372_MONOMER", "MG_380_MONOMER", "MG_381_MONOMER", "MG_391_MONOMER", "MG_398_MONOMER", "MG_402_MONOMER", "MG_424_MONOMER", "MG_425_MONOMER", "MG_427_MONOMER", "MG_438_MONOMER", "MG_439_MONOMER", "MG_446_MONOMER", "MG_458_MONOMER", "MG_469_MONOMER", "MG_473_MONOMER", "MG_498_MONOMER"]},
  {"name":"MG_252_MONOMER","imports":["MG_252_MONOMER", "MG_291_MONOMER", "MG_292_MONOMER"]},
  {"name":"MG_264_MONOMER","imports":["MG_134_MONOMER", "MG_143_MONOMER", "MG_264_MONOMER"]},
  {"name":"MG_268_MONOMER","imports":["MG_011_MONOMER", "MG_070_MONOMER", "MG_180_MONOMER", "MG_268_MONOMER", "MG_428_MONOMER"]},
  {"name":"MG_275_MONOMER","imports":["MG_022_MONOMER", "MG_024_MONOMER", "MG_026_MONOMER", "MG_027_MONOMER", "MG_028_MONOMER", "MG_043_MONOMER", "MG_044_MONOMER", "MG_050_MONOMER", "MG_054_MONOMER", "MG_055_MONOMER", "MG_056_MONOMER", "MG_069_MONOMER", "MG_070_MONOMER", "MG_084_MONOMER", "MG_088_MONOMER", "MG_094_MONOMER", "MG_097_MONOMER", "MG_105_MONOMER", "MG_125_MONOMER", "MG_141_MONOMER", "MG_153_MONOMER", "MG_169_MONOMER", "MG_239_MONOMER", "MG_275_MONOMER", "MG_281_MONOMER", "MG_282_MONOMER", "MG_336_MONOMER", "MG_337_MONOMER", "MG_338_MONOMER", "MG_360_MONOMER", "MG_363_MONOMER", "MG_402_MONOMER", "MG_405_MONOMER", "MG_439_MONOMER"]},
  {"name":"MG_281_MONOMER","imports":["MG_002_MONOMER", "MG_007_MONOMER", "MG_009_MONOMER", "MG_011_MONOMER", "MG_022_MONOMER", "MG_024_MONOMER", "MG_026_MONOMER", "MG_027_MONOMER", "MG_028_MONOMER", "MG_043_MONOMER", "MG_044_MONOMER", "MG_050_MONOMER", "MG_054_MONOMER", "MG_055_MONOMER", "MG_056_MONOMER", "MG_069_MONOMER", "MG_070_MONOMER", "MG_084_MONOMER", "MG_088_MONOMER", "MG_094_MONOMER", "MG_097_MONOMER", "MG_105_MONOMER", "MG_113_MONOMER", "MG_125_MONOMER", "MG_128_MONOMER", "MG_141_MONOMER", "MG_147_MONOMER", "MG_148_MONOMER", "MG_153_MONOMER", "MG_169_MONOMER", "MG_180_MONOMER", "MG_183_MONOMER", "MG_205_MONOMER", "MG_239_MONOMER", "MG_241_MONOMER", "MG_242_MONOMER", "MG_244_MONOMER", "MG_275_MONOMER", "MG_281_MONOMER", "MG_282_MONOMER", "MG_291_MONOMER", "MG_292_MONOMER", "MG_306_MONOMER", "MG_317_MONOMER", "MG_335_MONOMER", "MG_336_MONOMER", "MG_337_MONOMER", "MG_338_MONOMER", "MG_343_MONOMER", "MG_344_MONOMER", "MG_359_MONOMER", "MG_360_MONOMER", "MG_363_MONOMER", "MG_372_MONOMER", "MG_380_MONOMER", "MG_381_MONOMER", "MG_391_MONOMER", "MG_398_MONOMER", "MG_402_MONOMER", "MG_418_MONOMER", "MG_424_MONOMER", "MG_425_MONOMER", "MG_427_MONOMER", "MG_428_MONOMER", "MG_438_MONOMER", "MG_439_MONOMER", "MG_446_MONOMER", "MG_458_MONOMER", "MG_469_MONOMER", "MG_473_MONOMER", "MG_498_MONOMER"]},
  {"name":"MG_282_MONOMER","imports":["MG_002_MONOMER", "MG_007_MONOMER", "MG_009_MONOMER", "MG_011_MONOMER", "MG_022_MONOMER", "MG_024_MONOMER", "MG_026_MONOMER", "MG_027_MONOMER", "MG_028_MONOMER", "MG_043_MONOMER", "MG_044_MONOMER", "MG_050_MONOMER", "MG_054_MONOMER", "MG_055_MONOMER", "MG_056_MONOMER", "MG_069_MONOMER", "MG_070_MONOMER", "MG_084_MONOMER", "MG_088_MONOMER", "MG_094_MONOMER", "MG_097_MONOMER", "MG_105_MONOMER", "MG_113_MONOMER", "MG_125_MONOMER", "MG_128_MONOMER", "MG_141_MONOMER", "MG_147_MONOMER", "MG_148_MONOMER", "MG_153_MONOMER", "MG_169_MONOMER", "MG_180_MONOMER", "MG_183_MONOMER", "MG_205_MONOMER", "MG_239_MONOMER", "MG_241_MONOMER", "MG_242_MONOMER", "MG_244_MONOMER", "MG_275_MONOMER", "MG_281_MONOMER", "MG_282_MONOMER", "MG_291_MONOMER", "MG_292_MONOMER", "MG_306_MONOMER", "MG_317_MONOMER", "MG_335_MONOMER", "MG_336_MONOMER", "MG_337_MONOMER", "MG_338_MONOMER", "MG_343_MONOMER", "MG_344_MONOMER", "MG_360_MONOMER", "MG_363_MONOMER", "MG_372_MONOMER", "MG_380_MONOMER", "MG_381_MONOMER", "MG_391_MONOMER", "MG_398_MONOMER", "MG_402_MONOMER", "MG_418_MONOMER", "MG_424_MONOMER", "MG_425_MONOMER", "MG_427_MONOMER", "MG_428_MONOMER", "MG_438_MONOMER", "MG_439_MONOMER", "MG_446_MONOMER", "MG_458_MONOMER", "MG_469_MONOMER", "MG_473_MONOMER", "MG_498_MONOMER"]},
  {"name":"MG_290_MONOMER","imports":["MG_290_MONOMER", "MG_291_MONOMER", "MG_292_MONOMER"]},
  {"name":"MG_291_MONOMER","imports":["MG_002_MONOMER", "MG_007_MONOMER", "MG_024_MONOMER", "MG_027_MONOMER", "MG_028_MONOMER", "MG_050_MONOMER", "MG_055_MONOMER", "MG_056_MONOMER", "MG_069_MONOMER", "MG_070_MONOMER", "MG_088_MONOMER", "MG_094_MONOMER", "MG_097_MONOMER", "MG_125_MONOMER", "MG_148_MONOMER", "MG_183_MONOMER", "MG_239_MONOMER", "MG_244_MONOMER", "MG_252_MONOMER", "MG_281_MONOMER", "MG_282_MONOMER", "MG_290_MONOMER", "MG_291_MONOMER", "MG_292_MONOMER", "MG_300_MONOMER", "MG_336_MONOMER", "MG_337_MONOMER", "MG_344_MONOMER", "MG_402_MONOMER", "MG_425_MONOMER", "MG_427_MONOMER", "MG_428_MONOMER", "MG_438_MONOMER", "MG_439_MONOMER", "MG_469_MONOMER", "MG_473_MONOMER"]},
  {"name":"MG_292_MONOMER","imports":["MG_002_MONOMER", "MG_007_MONOMER", "MG_024_MONOMER", "MG_027_MONOMER", "MG_028_MONOMER", "MG_050_MONOMER", "MG_055_MONOMER", "MG_056_MONOMER", "MG_069_MONOMER", "MG_070_MONOMER", "MG_088_MONOMER", "MG_094_MONOMER", "MG_097_MONOMER", "MG_125_MONOMER", "MG_148_MONOMER", "MG_239_MONOMER", "MG_252_MONOMER", "MG_281_MONOMER", "MG_282_MONOMER", "MG_290_MONOMER", "MG_291_MONOMER", "MG_292_MONOMER", "MG_300_MONOMER", "MG_336_MONOMER", "MG_337_MONOMER", "MG_402_MONOMER", "MG_425_MONOMER", "MG_428_MONOMER", "MG_439_MONOMER", "MG_473_MONOMER"]},
  {"name":"MG_293_MONOMER","imports":["MG_022_MONOMER", "MG_043_MONOMER", "MG_044_MONOMER", "MG_293_MONOMER", "MG_360_MONOMER"]},
  {"name":"MG_300_MONOMER","imports":["MG_291_MONOMER", "MG_292_MONOMER", "MG_300_MONOMER"]},
  {"name":"MG_303_MONOMER","imports":["MG_303_MONOMER", "MG_405_MONOMER"]},
  {"name":"MG_306_MONOMER","imports":["MG_007_MONOMER", "MG_024_MONOMER", "MG_026_MONOMER", "MG_027_MONOMER", "MG_028_MONOMER", "MG_050_MONOMER", "MG_054_MONOMER", "MG_055_MONOMER", "MG_056_MONOMER", "MG_069_MONOMER", "MG_070_MONOMER", "MG_076_MONOMER", "MG_083_MONOMER", "MG_084_MONOMER", "MG_088_MONOMER", "MG_094_MONOMER", "MG_097_MONOMER", "MG_105_MONOMER", "MG_113_MONOMER", "MG_125_MONOMER", "MG_128_MONOMER", "MG_147_MONOMER", "MG_148_MONOMER", "MG_180_MONOMER", "MG_239_MONOMER", "MG_242_MONOMER", "MG_244_MONOMER", "MG_281_MONOMER", "MG_282_MONOMER", "MG_306_MONOMER", "MG_322_MONOMER", "MG_336_MONOMER", "MG_337_MONOMER", "MG_338_MONOMER", "MG_380_MONOMER", "MG_391_MONOMER", "MG_402_MONOMER", "MG_424_MONOMER", "MG_425_MONOMER", "MG_427_MONOMER", "MG_438_MONOMER", "MG_439_MONOMER", "MG_446_MONOMER", "MG_469_MONOMER"]},
  {"name":"MG_317_MONOMER","imports":["MG_007_MONOMER", "MG_024_MONOMER", "MG_026_MONOMER", "MG_027_MONOMER", "MG_028_MONOMER", "MG_043_MONOMER", "MG_044_MONOMER", "MG_050_MONOMER", "MG_054_MONOMER", "MG_055_MONOMER", "MG_056_MONOMER", "MG_069_MONOMER", "MG_070_MONOMER", "MG_088_MONOMER", "MG_094_MONOMER", "MG_097_MONOMER", "MG_125_MONOMER", "MG_180_MONOMER", "MG_183_MONOMER", "MG_239_MONOMER", "MG_241_MONOMER", "MG_242_MONOMER", "MG_244_MONOMER", "MG_281_MONOMER", "MG_282_MONOMER", "MG_317_MONOMER", "MG_336_MONOMER", "MG_337_MONOMER", "MG_360_MONOMER", "MG_380_MONOMER", "MG_402_MONOMER", "MG_425_MONOMER", "MG_427_MONOMER", "MG_438_MONOMER", "MG_439_MONOMER", "MG_446_MONOMER", "MG_469_MONOMER", "MG_473_MONOMER"]},
  {"name":"MG_322_MONOMER","imports":["MG_306_MONOMER", "MG_322_MONOMER"]},
  {"name":"MG_325_MONOMER","imports":["MG_325_MONOMER", "MG_326_MONOMER"]},
  {"name":"MG_326_MONOMER","imports":["MG_325_MONOMER", "MG_326_MONOMER"]},
  {"name":"MG_329_MONOMER","imports":["MG_190_MONOMER", "MG_329_MONOMER", "MG_330_MONOMER"]},
  {"name":"MG_330_MONOMER","imports":["MG_190_MONOMER", "MG_329_MONOMER", "MG_330_MONOMER"]},
  {"name":"MG_332_MONOMER","imports":["MG_332_MONOMER", "MG_460_MONOMER", "MG_478_MONOMER"]},
  {"name":"MG_335_MONOMER","imports":["MG_002_MONOMER", "MG_007_MONOMER", "MG_024_MONOMER", "MG_027_MONOMER", "MG_028_MONOMER", "MG_055_MONOMER", "MG_056_MONOMER", "MG_069_MONOMER", "MG_070_MONOMER", "MG_088_MONOMER", "MG_097_MONOMER", "MG_125_MONOMER", "MG_147_MONOMER", "MG_239_MONOMER", "MG_281_MONOMER", "MG_282_MONOMER", "MG_335_MONOMER", "MG_336_MONOMER", "MG_337_MONOMER", "MG_391_MONOMER", "MG_402_MONOMER", "MG_425_MONOMER", "MG_427_MONOMER", "MG_438_MONOMER", "MG_439_MONOMER", "MG_446_MONOMER", "MG_469_MONOMER"]},
  {"name":"MG_336_MONOMER","imports":["MG_002_MONOMER", "MG_007_MONOMER", "MG_009_MONOMER", "MG_011_MONOMER", "MG_022_MONOMER", "MG_024_MONOMER", "MG_026_MONOMER", "MG_027_MONOMER", "MG_028_MONOMER", "MG_043_MONOMER", "MG_044_MONOMER", "MG_050_MONOMER", "MG_054_MONOMER", "MG_055_MONOMER", "MG_056_MONOMER", "MG_069_MONOMER", "MG_070_MONOMER", "MG_084_MONOMER", "MG_088_MONOMER", "MG_094_MONOMER", "MG_097_MONOMER", "MG_105_MONOMER", "MG_113_MONOMER", "MG_125_MONOMER", "MG_128_MONOMER", "MG_141_MONOMER", "MG_147_MONOMER", "MG_148_MONOMER", "MG_153_MONOMER", "MG_169_MONOMER", "MG_180_MONOMER", "MG_183_MONOMER", "MG_205_MONOMER", "MG_239_MONOMER", "MG_241_MONOMER", "MG_242_MONOMER", "MG_244_MONOMER", "MG_275_MONOMER", "MG_281_MONOMER", "MG_282_MONOMER", "MG_291_MONOMER", "MG_292_MONOMER", "MG_306_MONOMER", "MG_317_MONOMER", "MG_335_MONOMER", "MG_336_MONOMER", "MG_337_MONOMER", "MG_338_MONOMER", "MG_343_MONOMER", "MG_344_MONOMER", "MG_359_MONOMER", "MG_360_MONOMER", "MG_363_MONOMER", "MG_372_MONOMER", "MG_380_MONOMER", "MG_381_MONOMER", "MG_391_MONOMER", "MG_398_MONOMER", "MG_402_MONOMER", "MG_418_MONOMER", "MG_424_MONOMER", "MG_425_MONOMER", "MG_427_MONOMER", "MG_428_MONOMER", "MG_438_MONOMER", "MG_439_MONOMER", "MG_446_MONOMER", "MG_458_MONOMER", "MG_469_MONOMER", "MG_473_MONOMER", "MG_498_MONOMER"]},
  {"name":"MG_337_MONOMER","imports":["MG_002_MONOMER", "MG_007_MONOMER", "MG_009_MONOMER", "MG_011_MONOMER", "MG_022_MONOMER", "MG_024_MONOMER", "MG_026_MONOMER", "MG_027_MONOMER", "MG_028_MONOMER", "MG_043_MONOMER", "MG_044_MONOMER", "MG_050_MONOMER", "MG_054_MONOMER", "MG_055_MONOMER", "MG_056_MONOMER", "MG_069_MONOMER", "MG_070_MONOMER", "MG_084_MONOMER", "MG_088_MONOMER", "MG_094_MONOMER", "MG_097_MONOMER", "MG_105_MONOMER", "MG_113_MONOMER", "MG_125_MONOMER", "MG_128_MONOMER", "MG_141_MONOMER", "MG_147_MONOMER", "MG_148_MONOMER", "MG_153_MONOMER", "MG_169_MONOMER", "MG_180_MONOMER", "MG_183_MONOMER", "MG_239_MONOMER", "MG_241_MONOMER", "MG_242_MONOMER", "MG_244_MONOMER", "MG_275_MONOMER", "MG_281_MONOMER", "MG_282_MONOMER", "MG_291_MONOMER", "MG_292_MONOMER", "MG_306_MONOMER", "MG_317_MONOMER", "MG_335_MONOMER", "MG_336_MONOMER", "MG_337_MONOMER", "MG_338_MONOMER", "MG_343_MONOMER", "MG_344_MONOMER", "MG_359_MONOMER", "MG_360_MONOMER", "MG_363_MONOMER", "MG_372_MONOMER", "MG_380_MONOMER", "MG_381_MONOMER", "MG_391_MONOMER", "MG_398_MONOMER", "MG_402_MONOMER", "MG_418_MONOMER", "MG_424_MONOMER", "MG_425_MONOMER", "MG_427_MONOMER", "MG_428_MONOMER", "MG_438_MONOMER", "MG_439_MONOMER", "MG_446_MONOMER", "MG_458_MONOMER", "MG_469_MONOMER", "MG_473_MONOMER", "MG_498_MONOMER"]},
  {"name":"MG_338_MONOMER","imports":["MG_002_MONOMER", "MG_024_MONOMER", "MG_028_MONOMER", "MG_050_MONOMER", "MG_055_MONOMER", "MG_069_MONOMER", "MG_070_MONOMER", "MG_084_MONOMER", "MG_088_MONOMER", "MG_097_MONOMER", "MG_105_MONOMER", "MG_124_MONOMER", "MG_125_MONOMER", "MG_128_MONOMER", "MG_141_MONOMER", "MG_217_MONOMER", "MG_239_MONOMER", "MG_275_MONOMER", "MG_281_MONOMER", "MG_282_MONOMER", "MG_306_MONOMER", "MG_336_MONOMER", "MG_337_MONOMER", "MG_338_MONOMER", "MG_363_MONOMER", "MG_402_MONOMER", "MG_439_MONOMER"]},
  {"name":"MG_343_MONOMER","imports":["MG_026_MONOMER", "MG_027_MONOMER", "MG_028_MONOMER", "MG_056_MONOMER", "MG_069_MONOMER", "MG_070_MONOMER", "MG_088_MONOMER", "MG_094_MONOMER", "MG_097_MONOMER", "MG_125_MONOMER", "MG_239_MONOMER", "MG_281_MONOMER", "MG_282_MONOMER", "MG_336_MONOMER", "MG_337_MONOMER", "MG_343_MONOMER", "MG_344_MONOMER", "MG_360_MONOMER", "MG_425_MONOMER", "MG_427_MONOMER", "MG_439_MONOMER"]},
  {"name":"MG_344_MONOMER","imports":["MG_007_MONOMER", "MG_009_MONOMER", "MG_011_MONOMER", "MG_024_MONOMER", "MG_026_MONOMER", "MG_027_MONOMER", "MG_028_MONOMER", "MG_043_MONOMER", "MG_044_MONOMER", "MG_050_MONOMER", "MG_054_MONOMER", "MG_055_MONOMER", "MG_056_MONOMER", "MG_069_MONOMER", "MG_070_MONOMER", "MG_088_MONOMER", "MG_094_MONOMER", "MG_097_MONOMER", "MG_105_MONOMER", "MG_125_MONOMER", "MG_128_MONOMER", "MG_147_MONOMER", "MG_148_MONOMER", "MG_169_MONOMER", "MG_180_MONOMER", "MG_183_MONOMER", "MG_239_MONOMER", "MG_242_MONOMER", "MG_244_MONOMER", "MG_281_MONOMER", "MG_282_MONOMER", "MG_291_MONOMER", "MG_336_MONOMER", "MG_337_MONOMER", "MG_343_MONOMER", "MG_344_MONOMER", "MG_363_MONOMER", "MG_381_MONOMER", "MG_398_MONOMER", "MG_402_MONOMER", "MG_418_MONOMER", "MG_425_MONOMER", "MG_427_MONOMER", "MG_438_MONOMER", "MG_439_MONOMER", "MG_446_MONOMER", "MG_458_MONOMER", "MG_469_MONOMER", "MG_473_MONOMER", "MG_498_MONOMER"]},
  {"name":"MG_359_MONOMER","imports":["MG_028_MONOMER", "MG_050_MONOMER", "MG_084_MONOMER", "MG_088_MONOMER", "MG_097_MONOMER", "MG_125_MONOMER", "MG_239_MONOMER", "MG_281_MONOMER", "MG_336_MONOMER", "MG_337_MONOMER", "MG_359_MONOMER", "MG_381_MONOMER", "MG_425_MONOMER", "MG_427_MONOMER", "MG_469_MONOMER"]},
  {"name":"MG_360_MONOMER","imports":["MG_022_MONOMER", "MG_024_MONOMER", "MG_026_MONOMER", "MG_027_MONOMER", "MG_028_MONOMER", "MG_043_MONOMER", "MG_044_MONOMER", "MG_054_MONOMER", "MG_055_MONOMER", "MG_056_MONOMER", "MG_069_MONOMER", "MG_070_MONOMER", "MG_088_MONOMER", "MG_094_MONOMER", "MG_097_MONOMER", "MG_125_MONOMER", "MG_141_MONOMER", "MG_153_MONOMER", "MG_183_MONOMER", "MG_239_MONOMER", "MG_244_MONOMER", "MG_275_MONOMER", "MG_281_MONOMER", "MG_282_MONOMER", "MG_293_MONOMER", "MG_317_MONOMER", "MG_336_MONOMER", "MG_337_MONOMER", "MG_343_MONOMER", "MG_360_MONOMER", "MG_363_MONOMER", "MG_402_MONOMER", "MG_405_MONOMER", "MG_406_MONOMER", "MG_424_MONOMER", "MG_425_MONOMER", "MG_427_MONOMER", "MG_439_MONOMER", "MG_469_MONOMER"]},
  {"name":"MG_363_MONOMER","imports":["MG_002_MONOMER", "MG_007_MONOMER", "MG_009_MONOMER", "MG_011_MONOMER", "MG_024_MONOMER", "MG_026_MONOMER", "MG_027_MONOMER", "MG_028_MONOMER", "MG_043_MONOMER", "MG_044_MONOMER", "MG_050_MONOMER", "MG_054_MONOMER", "MG_055_MONOMER", "MG_056_MONOMER", "MG_069_MONOMER", "MG_070_MONOMER", "MG_084_MONOMER", "MG_088_MONOMER", "MG_094_MONOMER", "MG_097_MONOMER", "MG_105_MONOMER", "MG_113_MONOMER", "MG_125_MONOMER", "MG_128_MONOMER", "MG_141_MONOMER", "MG_147_MONOMER", "MG_148_MONOMER", "MG_153_MONOMER", "MG_169_MONOMER", "MG_239_MONOMER", "MG_242_MONOMER", "MG_244_MONOMER", "MG_275_MONOMER", "MG_281_MONOMER", "MG_282_MONOMER", "MG_336_MONOMER", "MG_337_MONOMER", "MG_338_MONOMER", "MG_344_MONOMER", "MG_360_MONOMER", "MG_363_MONOMER", "MG_372_MONOMER", "MG_402_MONOMER", "MG_411_MONOMER", "MG_425_MONOMER", "MG_427_MONOMER", "MG_438_MONOMER", "MG_439_MONOMER", "MG_446_MONOMER", "MG_458_MONOMER", "MG_469_MONOMER", "MG_473_MONOMER"]},
  {"name":"MG_372_MONOMER","imports":["MG_002_MONOMER", "MG_007_MONOMER", "MG_024_MONOMER", "MG_026_MONOMER", "MG_027_MONOMER", "MG_028_MONOMER", "MG_050_MONOMER", "MG_054_MONOMER", "MG_055_MONOMER", "MG_056_MONOMER", "MG_069_MONOMER", "MG_070_MONOMER", "MG_088_MONOMER", "MG_094_MONOMER", "MG_097_MONOMER", "MG_105_MONOMER", "MG_125_MONOMER", "MG_128_MONOMER", "MG_147_MONOMER", "MG_148_MONOMER", "MG_239_MONOMER", "MG_244_MONOMER", "MG_281_MONOMER", "MG_282_MONOMER", "MG_336_MONOMER", "MG_337_MONOMER", "MG_363_MONOMER", "MG_372_MONOMER", "MG_398_MONOMER", "MG_402_MONOMER", "MG_425_MONOMER", "MG_427_MONOMER", "MG_438_MONOMER", "MG_439_MONOMER", "MG_469_MONOMER", "MG_473_MONOMER"]},
  {"name":"MG_378_MONOMER","imports":["MG_378_MONOMER", "MG_379_MONOMER"]},
  {"name":"MG_379_MONOMER","imports":["MG_378_MONOMER", "MG_379_MONOMER"]},
  {"name":"MG_380_MONOMER","imports":["MG_024_MONOMER", "MG_027_MONOMER", "MG_028_MONOMER", "MG_044_MONOMER", "MG_050_MONOMER", "MG_054_MONOMER", "MG_055_MONOMER", "MG_056_MONOMER", "MG_069_MONOMER", "MG_070_MONOMER", "MG_084_MONOMER", "MG_088_MONOMER", "MG_094_MONOMER", "MG_097_MONOMER", "MG_105_MONOMER", "MG_125_MONOMER", "MG_169_MONOMER", "MG_180_MONOMER", "MG_183_MONOMER", "MG_239_MONOMER", "MG_242_MONOMER", "MG_244_MONOMER", "MG_281_MONOMER", "MG_282_MONOMER", "MG_306_MONOMER", "MG_317_MONOMER", "MG_336_MONOMER", "MG_337_MONOMER", "MG_380_MONOMER", "MG_391_MONOMER", "MG_402_MONOMER", "MG_424_MONOMER", "MG_425_MONOMER", "MG_427_MONOMER", "MG_438_MONOMER", "MG_439_MONOMER", "MG_446_MONOMER", "MG_469_MONOMER", "MG_473_MONOMER"]},
  {"name":"MG_381_MONOMER","imports":["MG_002_MONOMER", "MG_007_MONOMER", "MG_024_MONOMER", "MG_026_MONOMER", "MG_027_MONOMER", "MG_028_MONOMER", "MG_043_MONOMER", "MG_044_MONOMER", "MG_050_MONOMER", "MG_054_MONOMER", "MG_055_MONOMER", "MG_056_MONOMER", "MG_069_MONOMER", "MG_070_MONOMER", "MG_088_MONOMER", "MG_094_MONOMER", "MG_095_MONOMER", "MG_097_MONOMER", "MG_113_MONOMER", "MG_125_MONOMER", "MG_147_MONOMER", "MG_148_MONOMER", "MG_169_MONOMER", "MG_180_MONOMER", "MG_183_MONOMER", "MG_205_MONOMER", "MG_239_MONOMER", "MG_244_MONOMER", "MG_281_MONOMER", "MG_282_MONOMER", "MG_336_MONOMER", "MG_337_MONOMER", "MG_344_MONOMER", "MG_359_MONOMER", "MG_381_MONOMER", "MG_391_MONOMER", "MG_402_MONOMER", "MG_424_MONOMER", "MG_425_MONOMER", "MG_427_MONOMER", "MG_434_MONOMER", "MG_438_MONOMER", "MG_439_MONOMER", "MG_446_MONOMER", "MG_469_MONOMER", "MG_473_MONOMER"]},
  {"name":"MG_390_MONOMER","imports":["MG_072_MONOMER", "MG_390_MONOMER", "MG_391_MONOMER", "MG_424_MONOMER", "MG_425_MONOMER", "MG_427_MONOMER", "MG_446_MONOMER"]},
  {"name":"MG_391_MONOMER","imports":["MG_002_MONOMER", "MG_024_MONOMER", "MG_027_MONOMER", "MG_028_MONOMER", "MG_054_MONOMER", "MG_055_MONOMER", "MG_056_MONOMER", "MG_069_MONOMER", "MG_070_MONOMER", "MG_088_MONOMER", "MG_094_MONOMER", "MG_097_MONOMER", "MG_105_MONOMER", "MG_125_MONOMER", "MG_147_MONOMER", "MG_183_MONOMER", "MG_239_MONOMER", "MG_244_MONOMER", "MG_281_MONOMER", "MG_282_MONOMER", "MG_306_MONOMER", "MG_335_MONOMER", "MG_336_MONOMER", "MG_337_MONOMER", "MG_380_MONOMER", "MG_381_MONOMER", "MG_390_MONOMER", "MG_391_MONOMER", "MG_402_MONOMER", "MG_424_MONOMER", "MG_425_MONOMER", "MG_427_MONOMER", "MG_438_MONOMER", "MG_439_MONOMER", "MG_446_MONOMER", "MG_469_MONOMER", "MG_473_MONOMER"]},
  {"name":"MG_398_MONOMER","imports":["MG_011_MONOMER", "MG_024_MONOMER", "MG_027_MONOMER", "MG_028_MONOMER", "MG_044_MONOMER", "MG_050_MONOMER", "MG_055_MONOMER", "MG_056_MONOMER", "MG_069_MONOMER", "MG_070_MONOMER", "MG_088_MONOMER", "MG_094_MONOMER", "MG_097_MONOMER", "MG_125_MONOMER", "MG_147_MONOMER", "MG_148_MONOMER", "MG_183_MONOMER", "MG_239_MONOMER", "MG_244_MONOMER", "MG_281_MONOMER", "MG_282_MONOMER", "MG_336_MONOMER", "MG_337_MONOMER", "MG_344_MONOMER", "MG_372_MONOMER", "MG_398_MONOMER", "MG_402_MONOMER", "MG_424_MONOMER", "MG_425_MONOMER", "MG_427_MONOMER", "MG_439_MONOMER", "MG_469_MONOMER"]},
  {"name":"MG_402_MONOMER","imports":["MG_002_MONOMER", "MG_007_MONOMER", "MG_011_MONOMER", "MG_022_MONOMER", "MG_024_MONOMER", "MG_026_MONOMER", "MG_027_MONOMER", "MG_028_MONOMER", "MG_043_MONOMER", "MG_044_MONOMER", "MG_050_MONOMER", "MG_054_MONOMER", "MG_055_MONOMER", "MG_056_MONOMER", "MG_069_MONOMER", "MG_070_MONOMER", "MG_088_MONOMER", "MG_094_MONOMER", "MG_097_MONOMER", "MG_105_MONOMER", "MG_113_MONOMER", "MG_125_MONOMER", "MG_128_MONOMER", "MG_141_MONOMER", "MG_147_MONOMER", "MG_148_MONOMER", "MG_153_MONOMER", "MG_180_MONOMER", "MG_183_MONOMER", "MG_239_MONOMER", "MG_241_MONOMER", "MG_242_MONOMER", "MG_244_MONOMER", "MG_275_MONOMER", "MG_281_MONOMER", "MG_282_MONOMER", "MG_291_MONOMER", "MG_292_MONOMER", "MG_306_MONOMER", "MG_317_MONOMER", "MG_335_MONOMER", "MG_336_MONOMER", "MG_337_MONOMER", "MG_338_MONOMER", "MG_344_MONOMER", "MG_360_MONOMER", "MG_363_MONOMER", "MG_372_MONOMER", "MG_380_MONOMER", "MG_381_MONOMER", "MG_391_MONOMER", "MG_398_MONOMER", "MG_402_MONOMER", "MG_424_MONOMER", "MG_425_MONOMER", "MG_427_MONOMER", "MG_428_MONOMER", "MG_438_MONOMER", "MG_439_MONOMER", "MG_446_MONOMER", "MG_458_MONOMER", "MG_469_MONOMER", "MG_473_MONOMER", "MG_498_MONOMER"]},
  {"name":"MG_405_MONOMER","imports":["MG_043_MONOMER", "MG_044_MONOMER", "MG_090_MONOMER", "MG_141_MONOMER", "MG_275_MONOMER", "MG_303_MONOMER", "MG_360_MONOMER", "MG_405_MONOMER"]},
  {"name":"MG_406_MONOMER","imports":["MG_044_MONOMER", "MG_360_MONOMER", "MG_406_MONOMER"]},
  {"name":"MG_411_MONOMER","imports":["MG_009_MONOMER", "MG_026_MONOMER", "MG_027_MONOMER", "MG_043_MONOMER", "MG_094_MONOMER", "MG_363_MONOMER", "MG_411_MONOMER"]},
  {"name":"MG_418_MONOMER","imports":["MG_009_MONOMER", "MG_027_MONOMER", "MG_028_MONOMER", "MG_094_MONOMER", "MG_097_MONOMER", "MG_125_MONOMER", "MG_147_MONOMER", "MG_148_MONOMER", "MG_239_MONOMER", "MG_281_MONOMER", "MG_282_MONOMER", "MG_336_MONOMER", "MG_337_MONOMER", "MG_344_MONOMER", "MG_418_MONOMER", "MG_425_MONOMER", "MG_427_MONOMER", "MG_439_MONOMER", "MG_446_MONOMER", "MG_458_MONOMER"]},
  {"name":"MG_424_MONOMER","imports":["MG_002_MONOMER", "MG_007_MONOMER", "MG_024_MONOMER", "MG_026_MONOMER", "MG_027_MONOMER", "MG_028_MONOMER", "MG_044_MONOMER", "MG_050_MONOMER", "MG_054_MONOMER", "MG_055_MONOMER", "MG_056_MONOMER", "MG_069_MONOMER", "MG_070_MONOMER", "MG_084_MONOMER", "MG_088_MONOMER", "MG_094_MONOMER", "MG_097_MONOMER", "MG_105_MONOMER", "MG_125_MONOMER", "MG_128_MONOMER", "MG_147_MONOMER", "MG_148_MONOMER", "MG_169_MONOMER", "MG_180_MONOMER", "MG_183_MONOMER", "MG_205_MONOMER", "MG_239_MONOMER", "MG_242_MONOMER", "MG_244_MONOMER", "MG_281_MONOMER", "MG_282_MONOMER", "MG_306_MONOMER", "MG_336_MONOMER", "MG_337_MONOMER", "MG_360_MONOMER", "MG_380_MONOMER", "MG_381_MONOMER", "MG_390_MONOMER", "MG_391_MONOMER", "MG_398_MONOMER", "MG_402_MONOMER", "MG_424_MONOMER", "MG_425_MONOMER", "MG_427_MONOMER", "MG_438_MONOMER", "MG_439_MONOMER", "MG_446_MONOMER", "MG_469_MONOMER", "MG_473_MONOMER"]},
  {"name":"MG_425_MONOMER","imports":["MG_002_MONOMER", "MG_007_MONOMER", "MG_011_MONOMER", "MG_024_MONOMER", "MG_026_MONOMER", "MG_027_MONOMER", "MG_028_MONOMER", "MG_043_MONOMER", "MG_044_MONOMER", "MG_050_MONOMER", "MG_054_MONOMER", "MG_055_MONOMER", "MG_056_MONOMER", "MG_069_MONOMER", "MG_070_MONOMER", "MG_084_MONOMER", "MG_088_MONOMER", "MG_094_MONOMER", "MG_097_MONOMER", "MG_105_MONOMER", "MG_113_MONOMER", "MG_125_MONOMER", "MG_128_MONOMER", "MG_147_MONOMER", "MG_148_MONOMER", "MG_169_MONOMER", "MG_180_MONOMER", "MG_183_MONOMER", "MG_205_MONOMER", "MG_239_MONOMER", "MG_241_MONOMER", "MG_242_MONOMER", "MG_244_MONOMER", "MG_281_MONOMER", "MG_282_MONOMER", "MG_291_MONOMER", "MG_292_MONOMER", "MG_306_MONOMER", "MG_317_MONOMER", "MG_335_MONOMER", "MG_336_MONOMER", "MG_337_MONOMER", "MG_343_MONOMER", "MG_344_MONOMER", "MG_359_MONOMER", "MG_360_MONOMER", "MG_363_MONOMER", "MG_372_MONOMER", "MG_380_MONOMER", "MG_381_MONOMER", "MG_390_MONOMER", "MG_391_MONOMER", "MG_398_MONOMER", "MG_402_MONOMER", "MG_418_MONOMER", "MG_424_MONOMER", "MG_425_MONOMER", "MG_427_MONOMER", "MG_428_MONOMER", "MG_438_MONOMER", "MG_439_MONOMER", "MG_446_MONOMER", "MG_458_MONOMER", "MG_469_MONOMER", "MG_473_MONOMER", "MG_498_MONOMER"]},
  {"name":"MG_427_MONOMER","imports":["MG_002_MONOMER", "MG_007_MONOMER", "MG_011_MONOMER", "MG_024_MONOMER", "MG_026_MONOMER", "MG_027_MONOMER", "MG_028_MONOMER", "MG_043_MONOMER", "MG_044_MONOMER", "MG_050_MONOMER", "MG_054_MONOMER", "MG_055_MONOMER", "MG_056_MONOMER", "MG_069_MONOMER", "MG_070_MONOMER", "MG_084_MONOMER", "MG_088_MONOMER", "MG_094_MONOMER", "MG_097_MONOMER", "MG_105_MONOMER", "MG_113_MONOMER", "MG_125_MONOMER", "MG_128_MONOMER", "MG_147_MONOMER", "MG_148_MONOMER", "MG_169_MONOMER", "MG_180_MONOMER", "MG_183_MONOMER", "MG_205_MONOMER", "MG_239_MONOMER", "MG_241_MONOMER", "MG_242_MONOMER", "MG_244_MONOMER", "MG_281_MONOMER", "MG_282_MONOMER", "MG_291_MONOMER", "MG_306_MONOMER", "MG_317_MONOMER", "MG_335_MONOMER", "MG_336_MONOMER", "MG_337_MONOMER", "MG_343_MONOMER", "MG_344_MONOMER", "MG_359_MONOMER", "MG_360_MONOMER", "MG_363_MONOMER", "MG_372_MONOMER", "MG_380_MONOMER", "MG_381_MONOMER", "MG_390_MONOMER", "MG_391_MONOMER", "MG_398_MONOMER", "MG_402_MONOMER", "MG_418_MONOMER", "MG_424_MONOMER", "MG_425_MONOMER", "MG_427_MONOMER", "MG_428_MONOMER", "MG_438_MONOMER", "MG_439_MONOMER", "MG_446_MONOMER", "MG_458_MONOMER", "MG_469_MONOMER", "MG_473_MONOMER", "MG_498_MONOMER"]},
  {"name":"MG_428_MONOMER","imports":["MG_007_MONOMER", "MG_022_MONOMER", "MG_024_MONOMER", "MG_026_MONOMER", "MG_027_MONOMER", "MG_028_MONOMER", "MG_044_MONOMER", "MG_055_MONOMER", "MG_056_MONOMER", "MG_069_MONOMER", "MG_070_MONOMER", "MG_088_MONOMER", "MG_094_MONOMER", "MG_097_MONOMER", "MG_125_MONOMER", "MG_147_MONOMER", "MG_148_MONOMER", "MG_239_MONOMER", "MG_268_MONOMER", "MG_281_MONOMER", "MG_282_MONOMER", "MG_291_MONOMER", "MG_292_MONOMER", "MG_336_MONOMER", "MG_337_MONOMER", "MG_402_MONOMER", "MG_425_MONOMER", "MG_427_MONOMER", "MG_428_MONOMER", "MG_439_MONOMER", "MG_469_MONOMER", "MG_473_MONOMER"]},
  {"name":"MG_434_MONOMER","imports":["MG_381_MONOMER", "MG_434_MONOMER"]},
  {"name":"MG_438_MONOMER","imports":["MG_002_MONOMER", "MG_007_MONOMER", "MG_009_MONOMER", "MG_024_MONOMER", "MG_026_MONOMER", "MG_027_MONOMER", "MG_028_MONOMER", "MG_043_MONOMER", "MG_044_MONOMER", "MG_050_MONOMER", "MG_054_MONOMER", "MG_055_MONOMER", "MG_056_MONOMER", "MG_069_MONOMER", "MG_070_MONOMER", "MG_088_MONOMER", "MG_094_MONOMER", "MG_097_MONOMER", "MG_105_MONOMER", "MG_113_MONOMER", "MG_125_MONOMER", "MG_128_MONOMER", "MG_147_MONOMER", "MG_148_MONOMER", "MG_169_MONOMER", "MG_180_MONOMER", "MG_183_MONOMER", "MG_239_MONOMER", "MG_242_MONOMER", "MG_244_MONOMER", "MG_281_MONOMER", "MG_282_MONOMER", "MG_291_MONOMER", "MG_306_MONOMER", "MG_317_MONOMER", "MG_335_MONOMER", "MG_336_MONOMER", "MG_337_MONOMER", "MG_344_MONOMER", "MG_363_MONOMER", "MG_372_MONOMER", "MG_380_MONOMER", "MG_381_MONOMER", "MG_391_MONOMER", "MG_402_MONOMER", "MG_424_MONOMER", "MG_425_MONOMER", "MG_427_MONOMER", "MG_438_MONOMER", "MG_439_MONOMER", "MG_446_MONOMER", "MG_458_MONOMER", "MG_469_MONOMER", "MG_473_MONOMER", "MG_498_MONOMER"]},
  {"name":"MG_439_MONOMER","imports":["MG_002_MONOMER", "MG_007_MONOMER", "MG_009_MONOMER", "MG_011_MONOMER", "MG_022_MONOMER", "MG_024_MONOMER", "MG_026_MONOMER", "MG_027_MONOMER", "MG_028_MONOMER", "MG_043_MONOMER", "MG_044_MONOMER", "MG_050_MONOMER", "MG_054_MONOMER", "MG_055_MONOMER", "MG_056_MONOMER", "MG_069_MONOMER", "MG_070_MONOMER", "MG_084_MONOMER", "MG_088_MONOMER", "MG_094_MONOMER", "MG_097_MONOMER", "MG_105_MONOMER", "MG_113_MONOMER", "MG_125_MONOMER", "MG_128_MONOMER", "MG_141_MONOMER", "MG_147_MONOMER", "MG_148_MONOMER", "MG_153_MONOMER", "MG_169_MONOMER", "MG_180_MONOMER", "MG_183_MONOMER", "MG_205_MONOMER", "MG_239_MONOMER", "MG_241_MONOMER", "MG_242_MONOMER", "MG_244_MONOMER", "MG_275_MONOMER", "MG_281_MONOMER", "MG_282_MONOMER", "MG_291_MONOMER", "MG_292_MONOMER", "MG_306_MONOMER", "MG_317_MONOMER", "MG_335_MONOMER", "MG_336_MONOMER", "MG_337_MONOMER", "MG_338_MONOMER", "MG_343_MONOMER", "MG_344_MONOMER", "MG_360_MONOMER", "MG_363_MONOMER", "MG_372_MONOMER", "MG_380_MONOMER", "MG_381_MONOMER", "MG_391_MONOMER", "MG_398_MONOMER", "MG_402_MONOMER", "MG_418_MONOMER", "MG_424_MONOMER", "MG_425_MONOMER", "MG_427_MONOMER", "MG_428_MONOMER", "MG_438_MONOMER", "MG_439_MONOMER", "MG_446_MONOMER", "MG_458_MONOMER", "MG_469_MONOMER", "MG_473_MONOMER", "MG_498_MONOMER"]},
  {"name":"MG_446_MONOMER","imports":["MG_002_MONOMER", "MG_007_MONOMER", "MG_024_MONOMER", "MG_026_MONOMER", "MG_027_MONOMER", "MG_028_MONOMER", "MG_043_MONOMER", "MG_044_MONOMER", "MG_050_MONOMER", "MG_054_MONOMER", "MG_055_MONOMER", "MG_056_MONOMER", "MG_069_MONOMER", "MG_070_MONOMER", "MG_088_MONOMER", "MG_094_MONOMER", "MG_097_MONOMER", "MG_105_MONOMER", "MG_125_MONOMER", "MG_128_MONOMER", "MG_147_MONOMER", "MG_148_MONOMER", "MG_180_MONOMER", "MG_183_MONOMER", "MG_239_MONOMER", "MG_242_MONOMER", "MG_244_MONOMER", "MG_281_MONOMER", "MG_282_MONOMER", "MG_306_MONOMER", "MG_317_MONOMER", "MG_335_MONOMER", "MG_336_MONOMER", "MG_337_MONOMER", "MG_344_MONOMER", "MG_363_MONOMER", "MG_380_MONOMER", "MG_381_MONOMER", "MG_390_MONOMER", "MG_391_MONOMER", "MG_402_MONOMER", "MG_418_MONOMER", "MG_424_MONOMER", "MG_425_MONOMER", "MG_427_MONOMER", "MG_438_MONOMER", "MG_439_MONOMER", "MG_446_MONOMER", "MG_469_MONOMER", "MG_473_MONOMER", "MG_498_MONOMER"]},
  {"name":"MG_452_MONOMER","imports":["MG_452_MONOMER", "MG_460_MONOMER"]},
  {"name":"MG_458_MONOMER","imports":["MG_007_MONOMER", "MG_009_MONOMER", "MG_026_MONOMER", "MG_027_MONOMER", "MG_028_MONOMER", "MG_043_MONOMER", "MG_044_MONOMER", "MG_050_MONOMER", "MG_054_MONOMER", "MG_055_MONOMER", "MG_056_MONOMER", "MG_069_MONOMER", "MG_070_MONOMER", "MG_088_MONOMER", "MG_094_MONOMER", "MG_097_MONOMER", "MG_125_MONOMER", "MG_147_MONOMER", "MG_148_MONOMER", "MG_239_MONOMER", "MG_244_MONOMER", "MG_281_MONOMER", "MG_282_MONOMER", "MG_336_MONOMER", "MG_337_MONOMER", "MG_344_MONOMER", "MG_363_MONOMER", "MG_402_MONOMER", "MG_418_MONOMER", "MG_425_MONOMER", "MG_427_MONOMER", "MG_438_MONOMER", "MG_439_MONOMER", "MG_458_MONOMER", "MG_469_MONOMER", "MG_473_MONOMER", "MG_498_MONOMER"]},
  {"name":"MG_459_MONOMER","imports":["MG_459_MONOMER", "MG_482_MONOMER"]},
  {"name":"MG_460_MONOMER","imports":["MG_332_MONOMER", "MG_452_MONOMER", "MG_460_MONOMER"]},
  {"name":"MG_462_MONOMER","imports":["MG_078_MONOMER", "MG_462_MONOMER"]},
  {"name":"MG_466_MONOMER","imports":["MG_138_MONOMER", "MG_466_MONOMER"]},
  {"name":"MG_467_MONOMER","imports":["MG_076_MONOMER", "MG_467_MONOMER"]},
  {"name":"MG_469_MONOMER","imports":["MG_007_MONOMER", "MG_011_MONOMER", "MG_024_MONOMER", "MG_026_MONOMER", "MG_027_MONOMER", "MG_028_MONOMER", "MG_043_MONOMER", "MG_044_MONOMER", "MG_050_MONOMER", "MG_054_MONOMER", "MG_055_MONOMER", "MG_056_MONOMER", "MG_069_MONOMER", "MG_070_MONOMER", "MG_084_MONOMER", "MG_088_MONOMER", "MG_094_MONOMER", "MG_097_MONOMER", "MG_105_MONOMER", "MG_125_MONOMER", "MG_128_MONOMER", "MG_141_MONOMER", "MG_147_MONOMER", "MG_148_MONOMER", "MG_153_MONOMER", "MG_180_MONOMER", "MG_183_MONOMER", "MG_205_MONOMER", "MG_239_MONOMER", "MG_241_MONOMER", "MG_242_MONOMER", "MG_243_MONOMER", "MG_244_MONOMER", "MG_281_MONOMER", "MG_282_MONOMER", "MG_291_MONOMER", "MG_306_MONOMER", "MG_317_MONOMER", "MG_335_MONOMER", "MG_336_MONOMER", "MG_337_MONOMER", "MG_344_MONOMER", "MG_359_MONOMER", "MG_360_MONOMER", "MG_363_MONOMER", "MG_372_MONOMER", "MG_380_MONOMER", "MG_381_MONOMER", "MG_391_MONOMER", "MG_398_MONOMER", "MG_402_MONOMER", "MG_424_MONOMER", "MG_425_MONOMER", "MG_427_MONOMER", "MG_428_MONOMER", "MG_438_MONOMER", "MG_439_MONOMER", "MG_446_MONOMER", "MG_458_MONOMER", "MG_469_MONOMER", "MG_473_MONOMER"]},
  {"name":"MG_473_MONOMER","imports":["MG_002_MONOMER", "MG_007_MONOMER", "MG_024_MONOMER", "MG_026_MONOMER", "MG_027_MONOMER", "MG_028_MONOMER", "MG_043_MONOMER", "MG_044_MONOMER", "MG_050_MONOMER", "MG_054_MONOMER", "MG_055_MONOMER", "MG_056_MONOMER", "MG_069_MONOMER", "MG_070_MONOMER", "MG_088_MONOMER", "MG_094_MONOMER", "MG_097_MONOMER", "MG_105_MONOMER", "MG_125_MONOMER", "MG_147_MONOMER", "MG_148_MONOMER", "MG_153_MONOMER", "MG_183_MONOMER", "MG_205_MONOMER", "MG_239_MONOMER", "MG_244_MONOMER", "MG_281_MONOMER", "MG_282_MONOMER", "MG_291_MONOMER", "MG_292_MONOMER", "MG_317_MONOMER", "MG_336_MONOMER", "MG_337_MONOMER", "MG_344_MONOMER", "MG_363_MONOMER", "MG_372_MONOMER", "MG_380_MONOMER", "MG_381_MONOMER", "MG_391_MONOMER", "MG_402_MONOMER", "MG_424_MONOMER", "MG_425_MONOMER", "MG_427_MONOMER", "MG_428_MONOMER", "MG_438_MONOMER", "MG_439_MONOMER", "MG_446_MONOMER", "MG_458_MONOMER", "MG_469_MONOMER", "MG_473_MONOMER"]},
  {"name":"MG_478_MONOMER","imports":["MG_332_MONOMER", "MG_478_MONOMER"]},
  {"name":"MG_482_MONOMER","imports":["MG_459_MONOMER", "MG_482_MONOMER"]},
  {"name":"MG_498_MONOMER","imports":["MG_007_MONOMER", "MG_024_MONOMER", "MG_027_MONOMER", "MG_028_MONOMER", "MG_041_MONOMER", "MG_050_MONOMER", "MG_054_MONOMER", "MG_055_MONOMER", "MG_056_MONOMER", "MG_069_MONOMER", "MG_070_MONOMER", "MG_088_MONOMER", "MG_094_MONOMER", "MG_097_MONOMER", "MG_125_MONOMER", "MG_128_MONOMER", "MG_183_MONOMER", "MG_214_MONOMER", "MG_239_MONOMER", "MG_242_MONOMER", "MG_244_MONOMER", "MG_281_MONOMER", "MG_282_MONOMER", "MG_336_MONOMER", "MG_337_MONOMER", "MG_344_MONOMER", "MG_402_MONOMER", "MG_425_MONOMER", "MG_427_MONOMER", "MG_438_MONOMER", "MG_439_MONOMER", "MG_446_MONOMER", "MG_458_MONOMER", "MG_498_MONOMER"]}
]
